{
  "api": [
    {
      "순번": "1",
      "강좌번호": "543",
      "과목코드": "1001119",
      "과목명": "생활과 윤리",
      "학부(과)": "중국어학과",
      "학년": "2",
      "이수구분": "교양필수",
      "영역구분": "인성교양",
      "학점": "2",
      "교수명": "송창호",
      "수업시간/장소": "화5~6(신학관103호강의실)",
      "수업시간": "화5~6",
      "장소": "신학관103호강의실"
    },
    {
      "순번": "2",
      "강좌번호": "538",
      "과목코드": "1004652",
      "과목명": "중국문학사 II",
      "학부(과)": "중국어학과",
      "학년": "2",
      "이수구분": "전공선택",
      "영역구분": "",
      "학점": "3",
      "교수명": "김낙철",
      "수업시간/장소": "월3(바울관403호강의실),수5~6(바울관402호강의실)",
      "수업시간": "월3,수5~6",
      "장소": "바울관402호강의실,바울관403호강의실"
    },
    {
      "순번": "3",
      "강좌번호": "537",
      "과목코드": "1004688",
      "과목명": "중국어연습II",
      "학부(과)": "중국어학과",
      "학년": "2",
      "이수구분": "전공선택",
      "영역구분": "",
      "학점": "3",
      "교수명": "박민수",
      "수업시간/장소": "월4(바울관402호강의실),목5~6(바울관403호강의실)",
      "수업시간": "월4,목5~6",
      "장소": "바울관402호강의실,바울관403호강의실"
    },
    {
      "순번": "4",
      "강좌번호": "539",
      "과목코드": "1004748",
      "과목명": "중급중국어 Ⅱ",
      "학부(과)": "중국어학과",
      "학년": "2",
      "이수구분": "전공선택",
      "영역구분": "",
      "학점": "3",
      "교수명": "함현자",
      "수업시간/장소": "화2~3(바울관402호강의실),수2(바울관402호강의실)",
      "수업시간": "화2~3,수2",
      "장소": "바울관402호강의실"
    },
    {
      "순번": "5",
      "강좌번호": "542",
      "과목코드": "1004758",
      "과목명": "중급중국어회화Ⅱ",
      "학부(과)": "중국어학과",
      "학년": "2",
      "이수구분": "전공선택",
      "영역구분": "",
      "학점": "3",
      "교수명": "진현",
      "수업시간/장소": "월1~2(바울관403호강의실),목1(바울관401호식음료실습실)",
      "수업시간": "월1~2,목1",
      "장소": "바울관401호식음료실습실,바울관403호강의실"
    },
    {
      "순번": "6",
      "강좌번호": "541",
      "과목코드": "1004758",
      "과목명": "중급중국어회화Ⅱ",
      "학부(과)": "중국어학과",
      "학년": "2",
      "이수구분": "전공선택",
      "영역구분": "",
      "학점": "3",
      "교수명": "갈장강",
      "수업시간/장소": "월1~2(바울관402호강의실),목1(바울관402호강의실)",
      "수업시간": "월1~2,목1",
      "장소": "바울관402호강의실"
    },
    {
      "순번": "7",
      "강좌번호": "1682",
      "과목코드": "1005656",
      "과목명": "현장어학실습",
      "학부(과)": "중국어학과",
      "학년": "2",
      "이수구분": "전공선택",
      "영역구분": "",
      "학점": "3",
      "교수명": "박민수",
      "수업시간/장소": "",
      "수업시간": "",
      "장소": ""
    },
    {
      "순번": "8",
      "강좌번호": "536",
      "과목코드": "1004903",
      "과목명": "채플",
      "학부(과)": "중국어학과",
      "학년": "2",
      "이수구분": "채플",
      "영역구분": "",
      "학점": "0",
      "교수명": "교목처",
      "수업시간/장소": "수3(미지정)",
      "수업시간": "수3",
      "장소": "미지정"
    },
    {
      "순번": "9",
      "강좌번호": "1745",
      "과목코드": "1001785",
      "과목명": "미디어중국어",
      "학부(과)": "중국어학과",
      "학년": "3",
      "이수구분": "교양필수",
      "영역구분": "",
      "학점": "2",
      "교수명": "옥계사범대학",
      "수업시간/장소": "",
      "수업시간": "",
      "장소": ""
    },
    {
      "순번": "10",
      "강좌번호": "1744",
      "과목코드": "1001847",
      "과목명": "민족풍습및음식문화",
      "학부(과)": "중국어학과",
      "학년": "3",
      "이수구분": "교양필수",
      "영역구분": "",
      "학점": "4",
      "교수명": "옥계사범대학",
      "수업시간/장소": "",
      "수업시간": "",
      "장소": ""
    },
    {
      "순번": "11",
      "강좌번호": "1727",
      "과목코드": "1000052",
      "과목명": "Ancient Chinese Literature",
      "학부(과)": "중국어학과",
      "학년": "3",
      "이수구분": "전공기초",
      "영역구분": "",
      "학점": "4",
      "교수명": "교류대학",
      "수업시간/장소": "",
      "수업시간": "",
      "장소": ""
    },
    {
      "순번": "12",
      "강좌번호": "1723",
      "과목코드": "1000051",
      "과목명": "Ancient Chinese",
      "학부(과)": "중국어학과",
      "학년": "3",
      "이수구분": "전공필수",
      "영역구분": "",
      "학점": "2",
      "교수명": "교류대학",
      "수업시간/장소": "",
      "수업시간": "",
      "장소": ""
    },
    {
      "순번": "13",
      "강좌번호": "1718",
      "과목코드": "1000696",
      "과목명": "고급중국어I",
      "학부(과)": "중국어학과",
      "학년": "3",
      "이수구분": "전공필수",
      "영역구분": "",
      "학점": "4",
      "교수명": "교류대학",
      "수업시간/장소": "",
      "수업시간": "",
      "장소": ""
    },
    {
      "순번": "14",
      "강좌번호": "1719",
      "과목코드": "1000704",
      "과목명": "고대한어",
      "학부(과)": "중국어학과",
      "학년": "3",
      "이수구분": "전공필수",
      "영역구분": "",
      "학점": "2",
      "교수명": "교류대학",
      "수업시간/장소": "",
      "수업시간": "",
      "장소": ""
    },
    {
      "순번": "15",
      "강좌번호": "1743",
      "과목코드": "1000704",
      "과목명": "고대한어",
      "학부(과)": "중국어학과",
      "학년": "3",
      "이수구분": "전공필수",
      "영역구분": "",
      "학점": "2",
      "교수명": "옥계사범대학",
      "수업시간/장소": "",
      "수업시간": "",
      "장소": ""
    },
    {
      "순번": "16",
      "강좌번호": "1747",
      "과목코드": "1004329",
      "과목명": "작문",
      "학부(과)": "중국어학과",
      "학년": "3",
      "이수구분": "전공필수",
      "영역구분": "",
      "학점": "4",
      "교수명": "옥계사범대학",
      "수업시간/장소": "",
      "수업시간": "",
      "장소": ""
    },
    {
      "순번": "17",
      "강좌번호": "1748",
      "과목코드": "1005627",
      "과목명": "현대중국어",
      "학부(과)": "중국어학과",
      "학년": "3",
      "이수구분": "전공필수",
      "영역구분": "",
      "학점": "3",
      "교수명": "옥계사범대학",
      "수업시간/장소": "",
      "수업시간": "",
      "장소": ""
    },
    {
      "순번": "18",
      "강좌번호": "1742",
      "과목코드": "1005628",
      "과목명": "현대중국어문법",
      "학부(과)": "중국어학과",
      "학년": "3",
      "이수구분": "전공필수",
      "영역구분": "",
      "학점": "4",
      "교수명": "옥계사범대학",
      "수업시간/장소": "",
      "수업시간": "",
      "장소": ""
    },
    {
      "순번": "19",
      "강좌번호": "1722",
      "과목코드": "1000137",
      "과목명": "Course of Chinese Lexicology",
      "학부(과)": "중국어학과",
      "학년": "3",
      "이수구분": "전공선택",
      "영역구분": "",
      "학점": "4",
      "교수명": "교류대학",
      "수업시간/장소": "",
      "수업시간": "",
      "장소": ""
    },
    {
      "순번": "20",
      "강좌번호": "549",
      "과목코드": "1000183",
      "과목명": "HSK특강 II",
      "학부(과)": "중국어학과",
      "학년": "3",
      "이수구분": "전공선택",
      "영역구분": "",
      "학점": "3",
      "교수명": "박민수",
      "수업시간/장소": "화1~3(바울관403호강의실)",
      "수업시간": "화1~3",
      "장소": "바울관403호강의실"
    },
    {
      "순번": "21",
      "강좌번호": "1725",
      "과목코드": "1000349",
      "과목명": "Topic Expressions",
      "학부(과)": "중국어학과",
      "학년": "3",
      "이수구분": "전공선택",
      "영역구분": "",
      "학점": "2",
      "교수명": "교류대학",
      "수업시간/장소": "",
      "수업시간": "",
      "장소": ""
    },
    {
      "순번": "22",
      "강좌번호": "545",
      "과목코드": "1000694",
      "과목명": "고급중국어 II",
      "학부(과)": "중국어학과",
      "학년": "3",
      "이수구분": "전공선택",
      "영역구분": "",
      "학점": "3",
      "교수명": "함현자",
      "수업시간/장소": "월6(바울관403호강의실),수5~6(바울관403호강의실)",
      "수업시간": "월6,수5~6",
      "장소": "바울관403호강의실"
    },
    {
      "순번": "23",
      "강좌번호": "546",
      "과목코드": "1000702",
      "과목명": "고급중국어회화 II",
      "학부(과)": "중국어학과",
      "학년": "3",
      "이수구분": "전공선택",
      "영역구분": "",
      "학점": "3",
      "교수명": "갈장강",
      "수업시간/장소": "월3(바울관312호강의실),목2~3(바울관403호강의실)",
      "수업시간": "월3,목2~3",
      "장소": "바울관312호강의실,바울관403호강의실"
    },
    {
      "순번": "24",
      "강좌번호": "1178",
      "과목코드": "1000702",
      "과목명": "고급중국어회화 II",
      "학부(과)": "중국어학과",
      "학년": "3",
      "이수구분": "전공선택",
      "영역구분": "",
      "학점": "3",
      "교수명": "진현",
      "수업시간/장소": "월3,목2~3",
      "수업시간": "월3,목2~3",
      "장소": ""
    },
    {
      "순번": "25",
      "강좌번호": "1751",
      "과목코드": "1001441",
      "과목명": "독해 I",
      "학부(과)": "중국어학과",
      "학년": "3",
      "이수구분": "전공선택",
      "영역구분": "",
      "학점": "4",
      "교수명": "중국하북대학",
      "수업시간/장소": "",
      "수업시간": "",
      "장소": ""
    },
    {
      "순번": "26",
      "강좌번호": "1749",
      "과목코드": "1003144",
      "과목명": "어법 I (하북교류)",
      "학부(과)": "중국어학과",
      "학년": "3",
      "이수구분": "전공선택",
      "영역구분": "",
      "학점": "4",
      "교수명": "중국하북대학",
      "수업시간/장소": "",
      "수업시간": "",
      "장소": ""
    },
    {
      "순번": "27",
      "강좌번호": "1753",
      "과목코드": "1004329",
      "과목명": "작문",
      "학부(과)": "중국어학과",
      "학년": "3",
      "이수구분": "전공선택",
      "영역구분": "",
      "학점": "2",
      "교수명": "중국하북대학",
      "수업시간/장소": "",
      "수업시간": "",
      "장소": ""
    },
    {
      "순번": "28",
      "강좌번호": "1752",
      "과목코드": "1004461",
      "과목명": "정독 II",
      "학부(과)": "중국어학과",
      "학년": "3",
      "이수구분": "전공선택",
      "영역구분": "",
      "학점": "6",
      "교수명": "중국하북대학",
      "수업시간/장소": "",
      "수업시간": "",
      "장소": ""
    },
    {
      "순번": "29",
      "강좌번호": "1726",
      "과목코드": "1004648",
      "과목명": "중국당대문학",
      "학부(과)": "중국어학과",
      "학년": "3",
      "이수구분": "전공선택",
      "영역구분": "",
      "학점": "4",
      "교수명": "교류대학",
      "수업시간/장소": "",
      "수업시간": "",
      "장소": ""
    },
    {
      "순번": "30",
      "강좌번호": "1720",
      "과목코드": "1004654",
      "과목명": "중국문화사",
      "학부(과)": "중국어학과",
      "학년": "3",
      "이수구분": "전공선택",
      "영역구분": "",
      "학점": "4",
      "교수명": "교류대학",
      "수업시간/장소": "",
      "수업시간": "",
      "장소": ""
    },
    {
      "순번": "31",
      "강좌번호": "1724",
      "과목코드": "1004701",
      "과목명": "중국역사",
      "학부(과)": "중국어학과",
      "학년": "3",
      "이수구분": "전공선택",
      "영역구분": "",
      "학점": "4",
      "교수명": "교류대학",
      "수업시간/장소": "",
      "수업시간": "",
      "장소": ""
    },
    {
      "순번": "32",
      "강좌번호": "547",
      "과목코드": "1004705",
      "과목명": "중국현대문학",
      "학부(과)": "중국어학과",
      "학년": "3",
      "이수구분": "전공선택",
      "영역구분": "",
      "학점": "3",
      "교수명": "신주석",
      "수업시간/장소": "수1~3(바울관403호강의실)",
      "수업시간": "수1~3",
      "장소": "바울관403호강의실"
    },
    {
      "순번": "33",
      "강좌번호": "1750",
      "과목코드": "1004746",
      "과목명": "중급읽고말하기",
      "학부(과)": "중국어학과",
      "학년": "3",
      "이수구분": "전공선택",
      "영역구분": "",
      "학점": "4",
      "교수명": "중국하북대학",
      "수업시간/장소": "",
      "수업시간": "",
      "장소": ""
    },
    {
      "순번": "34",
      "강좌번호": "548",
      "과목코드": "1005217",
      "과목명": "통역중국어 II",
      "학부(과)": "중국어학과",
      "학년": "3",
      "이수구분": "전공선택",
      "영역구분": "",
      "학점": "3",
      "교수명": "진현",
      "수업시간/장소": "월4(바울관403호강의실),목5~6(바울관303호(AIC프로젝트 LAB실))",
      "수업시간": "월4,목5~6",
      "장소": "바울관303호(AIC프로젝트 LAB실),바울관403호강의실"
    },
    {
      "순번": "35",
      "강좌번호": "1721",
      "과목코드": "1005626",
      "과목명": "현대중국문학",
      "학부(과)": "중국어학과",
      "학년": "3",
      "이수구분": "전공선택",
      "영역구분": "",
      "학점": "4",
      "교수명": "교류대학",
      "수업시간/장소": "",
      "수업시간": "",
      "장소": ""
    },
    {
      "순번": "36",
      "강좌번호": "1631",
      "과목코드": "1000834",
      "과목명": "교과교재연구 및 지도법",
      "학부(과)": "중국어학과",
      "학년": "3",
      "이수구분": "교직필수",
      "영역구분": "",
      "학점": "2",
      "교수명": "김낙철",
      "수업시간/장소": "화5~6(바울관312호강의실)",
      "수업시간": "화5~6",
      "장소": "바울관312호강의실"
    },
    {
      "순번": "37",
      "강좌번호": "544",
      "과목코드": "1004903",
      "과목명": "채플",
      "학부(과)": "중국어학과",
      "학년": "3",
      "이수구분": "채플",
      "영역구분": "",
      "학점": "0",
      "교수명": "미지정",
      "수업시간/장소": "월2(미지정)",
      "수업시간": "월2",
      "장소": "미지정"
    }
  ]
}