{
  "api": [
    {
      "순번": "1",
      "강좌번호": "289",
      "과목코드": "1001291",
      "과목명": "노작교육 I",
      "학부(과)": "신학과",
      "학년": "1",
      "이수구분": "교양필수",
      "영역구분": "",
      "학점": "1",
      "교수명": "한성보",
      "수업시간/장소": "목7~9(노작교육실습장)",
      "수업시간": "목7~9",
      "장소": "노작교육실습장"
    },
    {
      "순번": "2",
      "강좌번호": "286",
      "과목코드": "1002080",
      "과목명": "사고와 화술",
      "학부(과)": "신학과",
      "학년": "1",
      "이수구분": "교양필수",
      "영역구분": "",
      "학점": "2",
      "교수명": "이창호",
      "수업시간/장소": "월1~2",
      "수업시간": "월1~2",
      "장소": ""
    },
    {
      "순번": "3",
      "강좌번호": "290",
      "과목코드": "1002290",
      "과목명": "생활교육 I",
      "학부(과)": "신학과",
      "학년": "1",
      "이수구분": "교양필수",
      "영역구분": "",
      "학점": "1",
      "교수명": "김상래",
      "수업시간/장소": "월0,수0,금0",
      "수업시간": "월0,수0,금0",
      "장소": ""
    },
    {
      "순번": "4",
      "강좌번호": "291",
      "과목코드": "1002838",
      "과목명": "신학영어",
      "학부(과)": "신학과",
      "학년": "1",
      "이수구분": "교양필수",
      "영역구분": "",
      "학점": "2",
      "교수명": "Leander B. Chalice",
      "수업시간/장소": "화1~2(신학관208호(PBL소형)강의실)",
      "수업시간": "화1~2",
      "장소": "신학관208호(PBL소형)강의실"
    },
    {
      "순번": "5",
      "강좌번호": "288",
      "과목코드": "1002897",
      "과목명": "실용영어 I",
      "학부(과)": "신학과",
      "학년": "1",
      "이수구분": "교양필수",
      "영역구분": "",
      "학점": "3",
      "교수명": "Koo",
      "수업시간/장소": "월6,수2,목3",
      "수업시간": "월6,수2,목3",
      "장소": ""
    },
    {
      "순번": "6",
      "강좌번호": "287",
      "과목코드": "1002897",
      "과목명": "실용영어 I",
      "학부(과)": "신학과",
      "학년": "1",
      "이수구분": "교양필수",
      "영역구분": "",
      "학점": "3",
      "교수명": "Prof. Bacchus",
      "수업시간/장소": "월6,수2,목3",
      "수업시간": "월6,수2,목3",
      "장소": ""
    },
    {
      "순번": "7",
      "강좌번호": "292",
      "과목코드": "1000958",
      "과목명": "구약개론",
      "학부(과)": "신학과",
      "학년": "1",
      "이수구분": "전공필수",
      "영역구분": "",
      "학점": "3",
      "교수명": "한성보",
      "수업시간/장소": "월5(신학관208호(PBL소형)강의실),목1~2(신학관208호(PBL소형)강의실)",
      "수업시간": "월5,목1~2",
      "장소": "신학관208호(PBL소형)강의실"
    },
    {
      "순번": "8",
      "강좌번호": "798",
      "과목코드": "1004903",
      "과목명": "채플",
      "학부(과)": "신학과",
      "학년": "1",
      "이수구분": "채플",
      "영역구분": "",
      "학점": "0",
      "교수명": "미지정",
      "수업시간/장소": "월3(미지정),화3",
      "수업시간": "월3,화3",
      "장소": "미지정"
    },
    {
      "순번": "9",
      "강좌번호": "296",
      "과목코드": "1002292",
      "과목명": "생활교육 III",
      "학부(과)": "신학과",
      "학년": "2",
      "이수구분": "교양필수",
      "영역구분": "",
      "학점": "1",
      "교수명": "김상래",
      "수업시간/장소": "목5",
      "수업시간": "목5",
      "장소": ""
    },
    {
      "순번": "10",
      "강좌번호": "297",
      "과목코드": "1000836",
      "과목명": "교내선교 및 실습 I",
      "학부(과)": "신학과",
      "학년": "2",
      "이수구분": "전공기초",
      "영역구분": "",
      "학점": "0",
      "교수명": "김상래",
      "수업시간/장소": "화0(신학관201호강의실)",
      "수업시간": "화0",
      "장소": "신학관201호강의실"
    },
    {
      "순번": "11",
      "강좌번호": "301",
      "과목코드": "1003612",
      "과목명": "예언의 신",
      "학부(과)": "신학과",
      "학년": "2",
      "이수구분": "전공기초",
      "영역구분": "",
      "학점": "2",
      "교수명": "한성보",
      "수업시간/장소": "화2(신학관203호강의실),수6(신학관208호(PBL소형)강의실)",
      "수업시간": "화2,수6",
      "장소": "신학관203호강의실,신학관208호(PBL소형)강의실"
    },
    {
      "순번": "12",
      "강좌번호": "300",
      "과목코드": "1005048",
      "과목명": "초급헬라어 I",
      "학부(과)": "신학과",
      "학년": "2",
      "이수구분": "전공기초",
      "영역구분": "",
      "학점": "3",
      "교수명": "하홍팔",
      "수업시간/장소": "화1(신학관203호강의실),수1(신학관203호강의실),금1(신학관203호강의실)",
      "수업시간": "화1,수1,금1",
      "장소": "신학관203호강의실"
    },
    {
      "순번": "13",
      "강좌번호": "298",
      "과목코드": "1001649",
      "과목명": "모세오경",
      "학부(과)": "신학과",
      "학년": "2",
      "이수구분": "전공필수",
      "영역구분": "",
      "학점": "3",
      "교수명": "이종근",
      "수업시간/장소": "월7(신학관103호강의실),목5~6(신학관203호강의실)",
      "수업시간": "월7,목5~6",
      "장소": "신학관103호강의실,신학관203호강의실"
    },
    {
      "순번": "14",
      "강좌번호": "299",
      "과목코드": "1003597",
      "과목명": "예수의 생애와 교훈",
      "학부(과)": "신학과",
      "학년": "2",
      "이수구분": "전공필수",
      "영역구분": "",
      "학점": "3",
      "교수명": "하홍팔",
      "수업시간/장소": "화5(신학관203호강의실),목2~3(신학관203호강의실)",
      "수업시간": "화5,목2~3",
      "장소": "신학관203호강의실"
    },
    {
      "순번": "15",
      "강좌번호": "302",
      "과목코드": "1000482",
      "과목명": "개인전도법 및 실습",
      "학부(과)": "신학과",
      "학년": "2",
      "이수구분": "전공선택",
      "영역구분": "",
      "학점": "2",
      "교수명": "김성익",
      "수업시간/장소": "월1~2(신학관210호강의실)",
      "수업시간": "월1~2",
      "장소": "신학관210호강의실"
    },
    {
      "순번": "16",
      "강좌번호": "293",
      "과목코드": "1004903",
      "과목명": "채플",
      "학부(과)": "신학과",
      "학년": "2",
      "이수구분": "채플",
      "영역구분": "",
      "학점": "0",
      "교수명": "교목처",
      "수업시간/장소": "월3(미지정),화3",
      "수업시간": "월3,화3",
      "장소": "미지정"
    },
    {
      "순번": "17",
      "강좌번호": "335",
      "과목코드": "1001341",
      "과목명": "다니엘",
      "학부(과)": "신학과",
      "학년": "3",
      "이수구분": "전공기초",
      "영역구분": "",
      "학점": "2",
      "교수명": "김상래",
      "수업시간/장소": "목6(신학관209호(신학과스터디룸)),금3(신학관209호(신학과스터디룸))",
      "수업시간": "목6,금3",
      "장소": "신학관209호(신학과스터디룸)"
    },
    {
      "순번": "18",
      "강좌번호": "334",
      "과목코드": "1001667",
      "과목명": "목회실습 V",
      "학부(과)": "신학과",
      "학년": "3",
      "이수구분": "전공기초",
      "영역구분": "",
      "학점": "1",
      "교수명": "김은배",
      "수업시간/장소": "화0(신학관210호강의실)",
      "수업시간": "화0",
      "장소": "신학관210호강의실"
    },
    {
      "순번": "19",
      "강좌번호": "339",
      "과목코드": "1005802",
      "과목명": "히브리어문법",
      "학부(과)": "신학과",
      "학년": "3",
      "이수구분": "전공기초",
      "영역구분": "",
      "학점": "3",
      "교수명": "김상래",
      "수업시간/장소": "화5(신학관208호(PBL소형)강의실),목1~2(신학관209호(신학과스터디룸))",
      "수업시간": "화5,목1~2",
      "장소": "신학관208호(PBL소형)강의실,신학관209호(신학과스터디룸)"
    },
    {
      "순번": "20",
      "강좌번호": "338",
      "과목코드": "1002365",
      "과목명": "선교학개론",
      "학부(과)": "신학과",
      "학년": "3",
      "이수구분": "전공필수",
      "영역구분": "",
      "학점": "3",
      "교수명": "전한봉",
      "수업시간/장소": "월4(신학관203호강의실),수2~3(신학관203호강의실)",
      "수업시간": "월4,수2~3",
      "장소": "신학관203호강의실"
    },
    {
      "순번": "21",
      "강좌번호": "337",
      "과목코드": "1002375",
      "과목명": "설교법 I",
      "학부(과)": "신학과",
      "학년": "3",
      "이수구분": "전공필수",
      "영역구분": "",
      "학점": "3",
      "교수명": "김은배",
      "수업시간/장소": "월1~2(신학관203호강의실),수5(신학관203호강의실)",
      "수업시간": "월1~2,수5",
      "장소": "신학관203호강의실"
    },
    {
      "순번": "22",
      "강좌번호": "340",
      "과목코드": "1004577",
      "과목명": "조직신학I",
      "학부(과)": "신학과",
      "학년": "3",
      "이수구분": "전공필수",
      "영역구분": "",
      "학점": "3",
      "교수명": "안금영",
      "수업시간/장소": "화7~8(신학관203호강의실),수8(신학관203호강의실)",
      "수업시간": "화7~8,수8",
      "장소": "신학관203호강의실"
    },
    {
      "순번": "23",
      "강좌번호": "336",
      "과목코드": "1001139",
      "과목명": "기독교회사 I",
      "학부(과)": "신학과",
      "학년": "3",
      "이수구분": "전공선택",
      "영역구분": "",
      "학점": "3",
      "교수명": "오만규",
      "수업시간/장소": "목3(신학관208호(PBL소형)강의실),금1~2(신학관208호(PBL소형)강의실)",
      "수업시간": "목3,금1~2",
      "장소": "신학관208호(PBL소형)강의실"
    },
    {
      "순번": "24",
      "강좌번호": "333",
      "과목코드": "1002053",
      "과목명": "비교종교학",
      "학부(과)": "신학과",
      "학년": "3",
      "이수구분": "전공선택",
      "영역구분": "",
      "학점": "2",
      "교수명": "김기곤",
      "수업시간/장소": "화1(신학관202호강의실),수1(신학관202호강의실)",
      "수업시간": "화1,수1",
      "장소": "신학관202호강의실"
    },
    {
      "순번": "25",
      "강좌번호": "341",
      "과목코드": "1003588",
      "과목명": "예배학 및 실습",
      "학부(과)": "신학과",
      "학년": "3",
      "이수구분": "전공선택",
      "영역구분": "",
      "학점": "2",
      "교수명": "장병호",
      "수업시간/장소": "수6~7(신학관209호(신학과스터디룸))",
      "수업시간": "수6~7",
      "장소": "신학관209호(신학과스터디룸)"
    },
    {
      "순번": "26",
      "강좌번호": "332",
      "과목코드": "1000833",
      "과목명": "교과교육론",
      "학부(과)": "신학과",
      "학년": "3",
      "이수구분": "교직필수",
      "영역구분": "",
      "학점": "2",
      "교수명": "김성익",
      "수업시간/장소": "수6~7",
      "수업시간": "수6~7",
      "장소": ""
    },
    {
      "순번": "27",
      "강좌번호": "330",
      "과목코드": "1004903",
      "과목명": "채플",
      "학부(과)": "신학과",
      "학년": "3",
      "이수구분": "채플",
      "영역구분": "",
      "학점": "0",
      "교수명": "교목처",
      "수업시간/장소": "월3(미지정),화3",
      "수업시간": "월3,화3",
      "장소": "미지정"
    },
    {
      "순번": "28",
      "강좌번호": "346",
      "과목코드": "1001669",
      "과목명": "목회실습 VII",
      "학부(과)": "신학과",
      "학년": "4",
      "이수구분": "전공기초",
      "영역구분": "",
      "학점": "1",
      "교수명": "한성보",
      "수업시간/장소": "화0(신학관 채플실)",
      "수업시간": "화0",
      "장소": "신학관 채플실"
    },
    {
      "순번": "29",
      "강좌번호": "344",
      "과목코드": "1001855",
      "과목명": "바울서신",
      "학부(과)": "신학과",
      "학년": "4",
      "이수구분": "전공필수",
      "영역구분": "",
      "학점": "3",
      "교수명": "김기곤",
      "수업시간/장소": "월2(신학관202호강의실),수2~3(신학관202호강의실)",
      "수업시간": "월2,수2~3",
      "장소": "신학관202호강의실"
    },
    {
      "순번": "30",
      "강좌번호": "347",
      "과목코드": "1002368",
      "과목명": "선지서 I",
      "학부(과)": "신학과",
      "학년": "4",
      "이수구분": "전공필수",
      "영역구분": "",
      "학점": "3",
      "교수명": "남대극",
      "수업시간/장소": "월5~6(신학관202호강의실),목0(신학관202호강의실)",
      "수업시간": "월5~6,목0",
      "장소": "신학관202호강의실"
    },
    {
      "순번": "31",
      "강좌번호": "348",
      "과목코드": "1002533",
      "과목명": "소그룹전도와 양육",
      "학부(과)": "신학과",
      "학년": "4",
      "이수구분": "전공선택",
      "영역구분": "",
      "학점": "2",
      "교수명": "김성익",
      "수업시간/장소": "목1~2(신학관210호강의실)",
      "수업시간": "목1~2",
      "장소": "신학관210호강의실"
    },
    {
      "순번": "32",
      "강좌번호": "342",
      "과목코드": "1004903",
      "과목명": "채플",
      "학부(과)": "신학과",
      "학년": "4",
      "이수구분": "채플",
      "영역구분": "",
      "학점": "0",
      "교수명": "교목처",
      "수업시간/장소": "월3(미지정),화3",
      "수업시간": "월3,화3",
      "장소": "미지정"
    }
  ]
}