{
  "api": [
    {
      "순번": "1",
      "강좌번호": "2569",
      "과목코드": "1001058",
      "과목명": "글로벌리더십교육Ⅰ",
      "학부(과)": "상담심리학과",
      "학년": "1",
      "이수구분": "교양필수",
      "영역구분": "일반선택영역",
      "학점": "0",
      "교수명": "비젼드림센터3399-3076",
      "수업시간/장소": "",
      "수업시간": "",
      "장소": ""
    },
    {
      "순번": "2",
      "강좌번호": "1595",
      "과목코드": "1001135",
      "과목명": "종교와인생(구,기독교입문)",
      "학부(과)": "상담심리학과",
      "학년": "1",
      "이수구분": "교양필수",
      "영역구분": "인성교양",
      "학점": "2",
      "교수명": "김신섭",
      "수업시간/장소": "화1~2(다니엘관405호(大)강의실)",
      "수업시간": "화1~2",
      "장소": "다니엘관405호(大)강의실"
    },
    {
      "순번": "3",
      "강좌번호": "2785",
      "과목코드": "1002897",
      "과목명": "실용영어 I",
      "학부(과)": "상담심리학과",
      "학년": "1",
      "이수구분": "교양필수",
      "영역구분": "일반선택영역",
      "학점": "3",
      "교수명": "Valerie Janine S Pratt",
      "수업시간/장소": "월6(다니엘관204호(小)(교필토익전용)강의실),화6(다니엘관204호(小)(교필토익전용)강의실),수6(다니엘관204호(小)(교필토익전용)강의실),목6(다니엘관204호(小)(교필토익전용)강의실)",
      "수업시간": "월6,화6,수6,목6",
      "장소": "다니엘관204호(小)(교필토익전용)강의실"
    },
    {
      "순번": "4",
      "강좌번호": "2877",
      "과목코드": "1002897",
      "과목명": "실용영어 I",
      "학부(과)": "상담심리학과",
      "학년": "1",
      "이수구분": "교양필수",
      "영역구분": "일반선택영역",
      "학점": "3",
      "교수명": "Ramez Francis El-Haj",
      "수업시간/장소": "월6,화6,수6,목6",
      "수업시간": "월6,화6,수6,목6",
      "장소": ""
    },
    {
      "순번": "5",
      "강좌번호": "2786",
      "과목코드": "1002897",
      "과목명": "실용영어 I",
      "학부(과)": "상담심리학과",
      "학년": "1",
      "이수구분": "교양필수",
      "영역구분": "일반선택영역",
      "학점": "3",
      "교수명": "Baronese Harriet Peters",
      "수업시간/장소": "월6,화6,수6,목6",
      "수업시간": "월6,화6,수6,목6",
      "장소": ""
    },
    {
      "순번": "6",
      "강좌번호": "1592",
      "과목코드": "1002207",
      "과목명": "상담학개론",
      "학부(과)": "상담심리학과",
      "학년": "1",
      "이수구분": "전공선택",
      "영역구분": "",
      "학점": "3",
      "교수명": "김신섭",
      "수업시간/장소": "수1~3(다니엘관405호(大)강의실)",
      "수업시간": "수1~3",
      "장소": "다니엘관405호(大)강의실"
    },
    {
      "순번": "7",
      "강좌번호": "1591",
      "과목코드": "1002316",
      "과목명": "생활지도의 이해",
      "학부(과)": "상담심리학과",
      "학년": "1",
      "이수구분": "전공선택",
      "영역구분": "",
      "학점": "3",
      "교수명": "정성진",
      "수업시간/장소": "월1~3(다니엘관207호(大)강의실)",
      "수업시간": "월1~3",
      "장소": "다니엘관207호(大)강의실"
    },
    {
      "순번": "8",
      "강좌번호": "1593",
      "과목코드": "1002938",
      "과목명": "심리학개론",
      "학부(과)": "상담심리학과",
      "학년": "1",
      "이수구분": "전공선택",
      "영역구분": "",
      "학점": "3",
      "교수명": "서경현",
      "수업시간/장소": "월7(다니엘관B102호(大)취업특강강의실),화7~8(다니엘관B102호(大)취업특강강의실)",
      "수업시간": "월7,화7~8",
      "장소": "다니엘관B102호(大)취업특강강의실"
    },
    {
      "순번": "9",
      "강좌번호": "1594",
      "과목코드": "1004903",
      "과목명": "채플",
      "학부(과)": "상담심리학과",
      "학년": "1",
      "이수구분": "채플",
      "영역구분": "",
      "학점": "0",
      "교수명": "미지정",
      "수업시간/장소": "수4(제2과학관102호(세미나실))",
      "수업시간": "수4",
      "장소": "제2과학관102호(세미나실)"
    },
    {
      "순번": "10",
      "강좌번호": "1603",
      "과목코드": "1001119",
      "과목명": "생활과 윤리",
      "학부(과)": "상담심리학과",
      "학년": "2",
      "이수구분": "교양필수",
      "영역구분": "인성교양",
      "학점": "2",
      "교수명": "Baronese Harriet Peters",
      "수업시간/장소": "화1~2",
      "수업시간": "화1~2",
      "장소": ""
    },
    {
      "순번": "11",
      "강좌번호": "1599",
      "과목코드": "1002169",
      "과목명": "사회심리학",
      "학부(과)": "상담심리학과",
      "학년": "2",
      "이수구분": "전공선택",
      "영역구분": "",
      "학점": "3",
      "교수명": "정구철",
      "수업시간/장소": "목5~7(다니엘관405호(大)강의실)",
      "수업시간": "목5~7",
      "장소": "다니엘관405호(大)강의실"
    },
    {
      "순번": "12",
      "강좌번호": "1598",
      "과목코드": "1002206",
      "과목명": "상담의 이론과 실제",
      "학부(과)": "상담심리학과",
      "학년": "2",
      "이수구분": "전공선택",
      "영역구분": "",
      "학점": "3",
      "교수명": "정성진",
      "수업시간/장소": "수1~3(다니엘관207호(大)강의실)",
      "수업시간": "수1~3",
      "장소": "다니엘관207호(大)강의실"
    },
    {
      "순번": "13",
      "강좌번호": "2361",
      "과목코드": "1002400",
      "과목명": "성경적 상담",
      "학부(과)": "상담심리학과",
      "학년": "2",
      "이수구분": "전공선택",
      "영역구분": "",
      "학점": "3",
      "교수명": "Baronese Harriet Peters",
      "수업시간/장소": "목1~3(국제교육관223호(中)대학원강의실)",
      "수업시간": "목1~3",
      "장소": "국제교육관223호(中)대학원강의실"
    },
    {
      "순번": "14",
      "강좌번호": "1600",
      "과목코드": "1002967",
      "과목명": "아동상담",
      "학부(과)": "상담심리학과",
      "학년": "2",
      "이수구분": "전공선택",
      "영역구분": "",
      "학점": "3",
      "교수명": "정옥환",
      "수업시간/장소": "화5~7(사무엘관309호(大)강의실)",
      "수업시간": "화5~7",
      "장소": "사무엘관309호(大)강의실"
    },
    {
      "순번": "15",
      "강좌번호": "1601",
      "과목코드": "1005240",
      "과목명": "특수아상담",
      "학부(과)": "상담심리학과",
      "학년": "2",
      "이수구분": "전공선택",
      "영역구분": "",
      "학점": "3",
      "교수명": "정옥환",
      "수업시간/장소": "화8~10",
      "수업시간": "화8~10",
      "장소": ""
    },
    {
      "순번": "16",
      "강좌번호": "1602",
      "과목코드": "1004903",
      "과목명": "채플",
      "학부(과)": "상담심리학과",
      "학년": "2",
      "이수구분": "채플",
      "영역구분": "",
      "학점": "0",
      "교수명": "미지정",
      "수업시간/장소": "수4(제2과학관102호(세미나실))",
      "수업시간": "수4",
      "장소": "제2과학관102호(세미나실)"
    },
    {
      "순번": "17",
      "강좌번호": "1611",
      "과목코드": "1004613",
      "과목명": "종교와 대인관계",
      "학부(과)": "상담심리학과",
      "학년": "3",
      "이수구분": "교양필수",
      "영역구분": "인성교양",
      "학점": "2",
      "교수명": "최정환",
      "수업시간/장소": "월6~7(다니엘관303호(中)강의실)",
      "수업시간": "월6~7",
      "장소": "다니엘관303호(中)강의실"
    },
    {
      "순번": "18",
      "강좌번호": "1608",
      "과목코드": "1000510",
      "과목명": "건강심리학",
      "학부(과)": "상담심리학과",
      "학년": "3",
      "이수구분": "전공선택",
      "영역구분": "",
      "학점": "3",
      "교수명": "서경현",
      "수업시간/장소": "월1~3(다니엘관B102호(大)취업특강강의실)",
      "수업시간": "월1~3",
      "장소": "다니엘관B102호(大)취업특강강의실"
    },
    {
      "순번": "19",
      "강좌번호": "1610",
      "과목코드": "1001313",
      "과목명": "놀이치료",
      "학부(과)": "상담심리학과",
      "학년": "3",
      "이수구분": "전공선택",
      "영역구분": "",
      "학점": "2",
      "교수명": "문리학",
      "수업시간/장소": "목5~6(다니엘관403호(PBL)강의실)",
      "수업시간": "목5~6",
      "장소": "다니엘관403호(PBL)강의실"
    },
    {
      "순번": "20",
      "강좌번호": "1607",
      "과목코드": "1002205",
      "과목명": "상담윤리",
      "학부(과)": "상담심리학과",
      "학년": "3",
      "이수구분": "전공선택",
      "영역구분": "",
      "학점": "3",
      "교수명": "Baronese Harriet Peters",
      "수업시간/장소": "수1~3(국제교육관222호(中)강의실)",
      "수업시간": "수1~3",
      "장소": "국제교육관222호(中)강의실"
    },
    {
      "순번": "21",
      "강좌번호": "1606",
      "과목코드": "1002933",
      "과목명": "심리검사",
      "학부(과)": "상담심리학과",
      "학년": "3",
      "이수구분": "전공선택",
      "영역구분": "",
      "학점": "3",
      "교수명": "정구철",
      "수업시간/장소": "목1~3(다니엘관405호(大)강의실)",
      "수업시간": "목1~3",
      "장소": "다니엘관405호(大)강의실"
    },
    {
      "순번": "22",
      "강좌번호": "2574",
      "과목코드": "1002936",
      "과목명": "심리학 현장실습 I",
      "학부(과)": "상담심리학과",
      "학년": "3",
      "이수구분": "전공선택",
      "영역구분": "",
      "학점": "3",
      "교수명": "박종환",
      "수업시간/장소": "목9~11",
      "수업시간": "목9~11",
      "장소": ""
    },
    {
      "순번": "23",
      "강좌번호": "1609",
      "과목코드": "1002936",
      "과목명": "심리학 현장실습 I",
      "학부(과)": "상담심리학과",
      "학년": "3",
      "이수구분": "전공선택",
      "영역구분": "",
      "학점": "3",
      "교수명": "정구철",
      "수업시간/장소": "금5~7",
      "수업시간": "금5~7",
      "장소": ""
    },
    {
      "순번": "24",
      "강좌번호": "1605",
      "과목코드": "1004857",
      "과목명": "집단상담",
      "학부(과)": "상담심리학과",
      "학년": "3",
      "이수구분": "전공선택",
      "영역구분": "",
      "학점": "3",
      "교수명": "정성진",
      "수업시간/장소": "화1~3(다니엘관404호(大)강의실)",
      "수업시간": "화1~3",
      "장소": "다니엘관404호(大)강의실"
    },
    {
      "순번": "25",
      "강좌번호": "2575",
      "과목코드": "1004903",
      "과목명": "채플",
      "학부(과)": "상담심리학과",
      "학년": "3",
      "이수구분": "채플",
      "영역구분": "",
      "학점": "0",
      "교수명": "미지정",
      "수업시간/장소": "수4(제2과학관102호(세미나실))",
      "수업시간": "수4",
      "장소": "제2과학관102호(세미나실)"
    }
  ]
}