{
  "api": [
    {
      "순번": "1",
      "강좌번호": "756",
      "과목코드": "1001135",
      "과목명": "종교와인생(구,기독교입문)",
      "학부(과)": "생활체육학과",
      "학년": "1",
      "이수구분": "교양필수",
      "영역구분": "인성교양",
      "학점": "2",
      "교수명": "전한봉",
      "수업시간/장소": "월2~3(사무엘관201호강의실)",
      "수업시간": "월2~3",
      "장소": "사무엘관201호강의실"
    },
    {
      "순번": "2",
      "강좌번호": "1464",
      "과목코드": "1002897",
      "과목명": "실용영어 I",
      "학부(과)": "생활체육학과",
      "학년": "1",
      "이수구분": "교양필수",
      "영역구분": "",
      "학점": "3",
      "교수명": "",
      "수업시간/장소": "월1,수1,목1",
      "수업시간": "월1,수1,목1",
      "장소": ""
    },
    {
      "순번": "3",
      "강좌번호": "758",
      "과목코드": "1002897",
      "과목명": "실용영어 I",
      "학부(과)": "생활체육학과",
      "학년": "1",
      "이수구분": "교양필수",
      "영역구분": "",
      "학점": "3",
      "교수명": "Prof. Bissell",
      "수업시간/장소": "월1,수1,목1",
      "수업시간": "월1,수1,목1",
      "장소": ""
    },
    {
      "순번": "4",
      "강좌번호": "1465",
      "과목코드": "1002897",
      "과목명": "실용영어 I",
      "학부(과)": "생활체육학과",
      "학년": "1",
      "이수구분": "교양필수",
      "영역구분": "",
      "학점": "3",
      "교수명": "Baronese Harriet Peters",
      "수업시간/장소": "월1,수1,목1",
      "수업시간": "월1,수1,목1",
      "장소": ""
    },
    {
      "순번": "5",
      "강좌번호": "757",
      "과목코드": "1003158",
      "과목명": "언어와 문학",
      "학부(과)": "생활체육학과",
      "학년": "1",
      "이수구분": "교양필수",
      "영역구분": "",
      "학점": "2",
      "교수명": "이창호",
      "수업시간/장소": "수2~3(사무엘관107호강의실)",
      "수업시간": "수2~3",
      "장소": "사무엘관107호강의실"
    },
    {
      "순번": "6",
      "강좌번호": "759",
      "과목코드": "1000877",
      "과목명": "교육무용",
      "학부(과)": "생활체육학과",
      "학년": "1",
      "이수구분": "전공필수",
      "영역구분": "",
      "학점": "1",
      "교수명": "박승순",
      "수업시간/장소": "수5~6(체육관109호(무도관))",
      "수업시간": "수5~6",
      "장소": "체육관109호(무도관)"
    },
    {
      "순번": "7",
      "강좌번호": "1270",
      "과목코드": "1000877",
      "과목명": "교육무용",
      "학부(과)": "생활체육학과",
      "학년": "1",
      "이수구분": "전공필수",
      "영역구분": "",
      "학점": "1",
      "교수명": "박승순",
      "수업시간/장소": "수7~8(체육관109호(무도관))",
      "수업시간": "수7~8",
      "장소": "체육관109호(무도관)"
    },
    {
      "순번": "8",
      "강좌번호": "764",
      "과목코드": "1002318",
      "과목명": "생활체육개론",
      "학부(과)": "생활체육학과",
      "학년": "1",
      "이수구분": "전공필수",
      "영역구분": "",
      "학점": "3",
      "교수명": "정동근",
      "수업시간/장소": "화1~2(체육관107호(세미나실)-불가),화4(체육관107호(세미나실)-불가)",
      "수업시간": "화1~2,화4",
      "장소": "체육관107호(세미나실)-불가"
    },
    {
      "순번": "9",
      "강좌번호": "1269",
      "과목코드": "1004987",
      "과목명": "체조 I",
      "학부(과)": "생활체육학과",
      "학년": "1",
      "이수구분": "전공필수",
      "영역구분": "",
      "학점": "1",
      "교수명": "전영석",
      "수업시간/장소": "금1~2(체육관)",
      "수업시간": "금1~2",
      "장소": "체육관"
    },
    {
      "순번": "10",
      "강좌번호": "762",
      "과목코드": "1004987",
      "과목명": "체조 I",
      "학부(과)": "생활체육학과",
      "학년": "1",
      "이수구분": "전공필수",
      "영역구분": "",
      "학점": "1",
      "교수명": "전영석",
      "수업시간/장소": "금3~4(체육관)",
      "수업시간": "금3~4",
      "장소": "체육관"
    },
    {
      "순번": "11",
      "강좌번호": "761",
      "과목코드": "1005184",
      "과목명": "태권도 I",
      "학부(과)": "생활체육학과",
      "학년": "1",
      "이수구분": "전공필수",
      "영역구분": "",
      "학점": "1",
      "교수명": "박승용",
      "수업시간/장소": "월5~6(체육관109호(무도관))",
      "수업시간": "월5~6",
      "장소": "체육관109호(무도관)"
    },
    {
      "순번": "12",
      "강좌번호": "1272",
      "과목코드": "1005184",
      "과목명": "태권도 I",
      "학부(과)": "생활체육학과",
      "학년": "1",
      "이수구분": "전공필수",
      "영역구분": "",
      "학점": "1",
      "교수명": "박승용",
      "수업시간/장소": "월7~8(체육관109호(무도관))",
      "수업시간": "월7~8",
      "장소": "체육관109호(무도관)"
    },
    {
      "순번": "13",
      "강좌번호": "763",
      "과목코드": "1001907",
      "과목명": "배구",
      "학부(과)": "생활체육학과",
      "학년": "1",
      "이수구분": "전공선택",
      "영역구분": "",
      "학점": "1",
      "교수명": "유광욱",
      "수업시간/장소": "화5~6(체육관)",
      "수업시간": "화5~6",
      "장소": "체육관"
    },
    {
      "순번": "14",
      "강좌번호": "1642",
      "과목코드": "1001907",
      "과목명": "배구",
      "학부(과)": "생활체육학과",
      "학년": "1",
      "이수구분": "전공선택",
      "영역구분": "",
      "학점": "1",
      "교수명": "유광욱",
      "수업시간/장소": "수7~8(체육관)",
      "수업시간": "수7~8",
      "장소": "체육관"
    },
    {
      "순번": "15",
      "강좌번호": "1273",
      "과목코드": "1001907",
      "과목명": "배구",
      "학부(과)": "생활체육학과",
      "학년": "1",
      "이수구분": "전공선택",
      "영역구분": "",
      "학점": "1",
      "교수명": "유광욱",
      "수업시간/장소": "목4~5(체육관)",
      "수업시간": "목4~5",
      "장소": "체육관"
    },
    {
      "순번": "16",
      "강좌번호": "760",
      "과목코드": "1003902",
      "과목명": "육상 I",
      "학부(과)": "생활체육학과",
      "학년": "1",
      "이수구분": "전공선택",
      "영역구분": "",
      "학점": "1",
      "교수명": "이재구",
      "수업시간/장소": "금5~6(체육관)",
      "수업시간": "금5~6",
      "장소": "체육관"
    },
    {
      "순번": "17",
      "강좌번호": "1271",
      "과목코드": "1003902",
      "과목명": "육상 I",
      "학부(과)": "생활체육학과",
      "학년": "1",
      "이수구분": "전공선택",
      "영역구분": "",
      "학점": "1",
      "교수명": "이재구",
      "수업시간/장소": "금3~4(체육관)",
      "수업시간": "금3~4",
      "장소": "체육관"
    },
    {
      "순번": "18",
      "강좌번호": "755",
      "과목코드": "1004903",
      "과목명": "채플",
      "학부(과)": "생활체육학과",
      "학년": "1",
      "이수구분": "채플",
      "영역구분": "",
      "학점": "0",
      "교수명": "미지정",
      "수업시간/장소": "화3(미지정)",
      "수업시간": "화3",
      "장소": "미지정"
    },
    {
      "순번": "19",
      "강좌번호": "1443",
      "과목코드": "1001946",
      "과목명": "보건복지교육",
      "학부(과)": "생활체육학과",
      "학년": "2",
      "이수구분": "교양필수",
      "영역구분": "",
      "학점": "2",
      "교수명": "오복자",
      "수업시간/장소": "목7~8",
      "수업시간": "목7~8",
      "장소": ""
    },
    {
      "순번": "20",
      "강좌번호": "344",
      "과목코드": "1002413",
      "과목명": "성서 역사",
      "학부(과)": "생활체육학과",
      "학년": "2",
      "이수구분": "교양필수",
      "영역구분": "인성교양",
      "학점": "2",
      "교수명": "구일회",
      "수업시간/장소": "화1~2(사무엘관208호강의실)",
      "수업시간": "화1~2",
      "장소": "사무엘관208호강의실"
    },
    {
      "순번": "21",
      "강좌번호": "352",
      "과목코드": "1002634",
      "과목명": "스포츠심리학",
      "학부(과)": "생활체육학과",
      "학년": "2",
      "이수구분": "전공기초",
      "영역구분": "",
      "학점": "3",
      "교수명": "원유병",
      "수업시간/장소": "수1~3(사무엘관208호강의실)",
      "수업시간": "수1~3",
      "장소": "사무엘관208호강의실"
    },
    {
      "순번": "22",
      "강좌번호": "349",
      "과목코드": "1003666",
      "과목명": "운동생리학",
      "학부(과)": "생활체육학과",
      "학년": "2",
      "이수구분": "전공기초",
      "영역구분": "",
      "학점": "4",
      "교수명": "이재구",
      "수업시간/장소": "월1~2(체육관107호(세미나실)-불가),금1~2(체육관107호(세미나실)-불가)",
      "수업시간": "월1~2,금1~2",
      "장소": "체육관107호(세미나실)-불가"
    },
    {
      "순번": "23",
      "강좌번호": "345",
      "과목코드": "1002560",
      "과목명": "수영 I",
      "학부(과)": "생활체육학과",
      "학년": "2",
      "이수구분": "전공필수",
      "영역구분": "",
      "학점": "1",
      "교수명": "김종구",
      "수업시간/장소": "수7~8",
      "수업시간": "수7~8",
      "장소": ""
    },
    {
      "순번": "24",
      "강좌번호": "1274",
      "과목코드": "1002560",
      "과목명": "수영 I",
      "학부(과)": "생활체육학과",
      "학년": "2",
      "이수구분": "전공필수",
      "영역구분": "",
      "학점": "1",
      "교수명": "김종구",
      "수업시간/장소": "수5~6",
      "수업시간": "수5~6",
      "장소": ""
    },
    {
      "순번": "25",
      "강좌번호": "347",
      "과목코드": "1000724",
      "과목명": "골프",
      "학부(과)": "생활체육학과",
      "학년": "2",
      "이수구분": "전공선택",
      "영역구분": "",
      "학점": "1",
      "교수명": "정동근",
      "수업시간/장소": "목1~2(체육관)",
      "수업시간": "목1~2",
      "장소": "체육관"
    },
    {
      "순번": "26",
      "강좌번호": "351",
      "과목코드": "1001570",
      "과목명": "레크레이션",
      "학부(과)": "생활체육학과",
      "학년": "2",
      "이수구분": "전공선택",
      "영역구분": "",
      "학점": "1",
      "교수명": "홍계희",
      "수업시간/장소": "금5~6",
      "수업시간": "금5~6",
      "장소": ""
    },
    {
      "순번": "27",
      "강좌번호": "1276",
      "과목코드": "1001989",
      "과목명": "볼링",
      "학부(과)": "생활체육학과",
      "학년": "2",
      "이수구분": "전공선택",
      "영역구분": "",
      "학점": "1",
      "교수명": "김은경",
      "수업시간/장소": "수7~8(체육관308호-불가)",
      "수업시간": "수7~8",
      "장소": "체육관308호-불가"
    },
    {
      "순번": "28",
      "강좌번호": "348",
      "과목코드": "1001989",
      "과목명": "볼링",
      "학부(과)": "생활체육학과",
      "학년": "2",
      "이수구분": "전공선택",
      "영역구분": "",
      "학점": "1",
      "교수명": "김은경",
      "수업시간/장소": "수5~6(체육관)",
      "수업시간": "수5~6",
      "장소": "체육관"
    },
    {
      "순번": "29",
      "강좌번호": "1277",
      "과목코드": "1002647",
      "과목명": "승마",
      "학부(과)": "생활체육학과",
      "학년": "2",
      "이수구분": "전공선택",
      "영역구분": "",
      "학점": "1",
      "교수명": "문석주",
      "수업시간/장소": "목5~6(체육관)",
      "수업시간": "목5~6",
      "장소": "체육관"
    },
    {
      "순번": "30",
      "강좌번호": "346",
      "과목코드": "1005187",
      "과목명": "테니스 I",
      "학부(과)": "생활체육학과",
      "학년": "2",
      "이수구분": "전공선택",
      "영역구분": "",
      "학점": "1",
      "교수명": "정동근",
      "수업시간/장소": "월5~6(체육관)",
      "수업시간": "월5~6",
      "장소": "체육관"
    },
    {
      "순번": "31",
      "강좌번호": "1275",
      "과목코드": "1005187",
      "과목명": "테니스 I",
      "학부(과)": "생활체육학과",
      "학년": "2",
      "이수구분": "전공선택",
      "영역구분": "",
      "학점": "1",
      "교수명": "정동근",
      "수업시간/장소": "월7~8(체육관)",
      "수업시간": "월7~8",
      "장소": "체육관"
    },
    {
      "순번": "32",
      "강좌번호": "350",
      "과목코드": "1005247",
      "과목명": "특수체육론",
      "학부(과)": "생활체육학과",
      "학년": "2",
      "이수구분": "전공선택",
      "영역구분": "",
      "학점": "2",
      "교수명": "강승애",
      "수업시간/장소": "화3~4",
      "수업시간": "화3~4",
      "장소": ""
    },
    {
      "순번": "33",
      "강좌번호": "1344",
      "과목코드": "1004903",
      "과목명": "채플",
      "학부(과)": "생활체육학과",
      "학년": "2",
      "이수구분": "채플",
      "영역구분": "",
      "학점": "0",
      "교수명": "미지정",
      "수업시간/장소": "월3(미지정)",
      "수업시간": "월3",
      "장소": "미지정"
    },
    {
      "순번": "34",
      "강좌번호": "360",
      "과목코드": "1002624",
      "과목명": "스포츠마케팅",
      "학부(과)": "생활체육학과",
      "학년": "3",
      "이수구분": "전공필수",
      "영역구분": "",
      "학점": "3",
      "교수명": "김한주",
      "수업시간/장소": "금3~5(체육관)",
      "수업시간": "금3~5",
      "장소": "체육관"
    },
    {
      "순번": "35",
      "강좌번호": "1520",
      "과목코드": "1001851",
      "과목명": "바디컨디셔닝",
      "학부(과)": "생활체육학과",
      "학년": "3",
      "이수구분": "전공선택",
      "영역구분": "",
      "학점": "2",
      "교수명": "박승순",
      "수업시간/장소": "화1~2",
      "수업시간": "화1~2",
      "장소": ""
    },
    {
      "순번": "36",
      "강좌번호": "354",
      "과목코드": "1001909",
      "과목명": "배드민턴",
      "학부(과)": "생활체육학과",
      "학년": "3",
      "이수구분": "전공선택",
      "영역구분": "",
      "학점": "1",
      "교수명": "김경란",
      "수업시간/장소": "월5~6(체육관)",
      "수업시간": "월5~6",
      "장소": "체육관"
    },
    {
      "순번": "37",
      "강좌번호": "359",
      "과목코드": "1002623",
      "과목명": "스포츠마사지",
      "학부(과)": "생활체육학과",
      "학년": "3",
      "이수구분": "전공선택",
      "영역구분": "",
      "학점": "2",
      "교수명": "김명기",
      "수업시간/장소": "목1~2(체육관)",
      "수업시간": "목1~2",
      "장소": "체육관"
    },
    {
      "순번": "38",
      "강좌번호": "1537",
      "과목코드": "1002637",
      "과목명": "스포츠약리학",
      "학부(과)": "생활체육학과",
      "학년": "3",
      "이수구분": "전공선택",
      "영역구분": "",
      "학점": "2",
      "교수명": "최성숙",
      "수업시간/장소": "수5~6(체육관)",
      "수업시간": "수5~6",
      "장소": "체육관"
    },
    {
      "순번": "39",
      "강좌번호": "358",
      "과목코드": "1002638",
      "과목명": "스포츠영양학",
      "학부(과)": "생활체육학과",
      "학년": "3",
      "이수구분": "전공선택",
      "영역구분": "",
      "학점": "2",
      "교수명": "김민정",
      "수업시간/장소": "화5~6(체육관)",
      "수업시간": "화5~6",
      "장소": "체육관"
    },
    {
      "순번": "40",
      "강좌번호": "357",
      "과목코드": "1003951",
      "과목명": "응급처치",
      "학부(과)": "생활체육학과",
      "학년": "3",
      "이수구분": "전공선택",
      "영역구분": "",
      "학점": "1",
      "교수명": "유재현",
      "수업시간/장소": "수1~2(체육관)",
      "수업시간": "수1~2",
      "장소": "체육관"
    },
    {
      "순번": "41",
      "강좌번호": "355",
      "과목코드": "1004422",
      "과목명": "전문실기I",
      "학부(과)": "생활체육학과",
      "학년": "3",
      "이수구분": "전공선택",
      "영역구분": "",
      "학점": "1",
      "교수명": "김갑수",
      "수업시간/장소": "월7~8(체육관)",
      "수업시간": "월7~8",
      "장소": "체육관"
    },
    {
      "순번": "42",
      "강좌번호": "356",
      "과목코드": "1005074",
      "과목명": "측정평가 및 통계",
      "학부(과)": "생활체육학과",
      "학년": "3",
      "이수구분": "전공선택",
      "영역구분": "",
      "학점": "3",
      "교수명": "김미예",
      "수업시간/장소": "월1~3(체육관)",
      "수업시간": "월1~3",
      "장소": "체육관"
    },
    {
      "순번": "43",
      "강좌번호": "1686",
      "과목코드": "1004975",
      "과목명": "체육교과교육론",
      "학부(과)": "생활체육학과",
      "학년": "3",
      "이수구분": "일반선택",
      "영역구분": "",
      "학점": "2",
      "교수명": "미지정",
      "수업시간/장소": "",
      "수업시간": "",
      "장소": ""
    },
    {
      "순번": "44",
      "강좌번호": "1278",
      "과목코드": "1004903",
      "과목명": "채플",
      "학부(과)": "생활체육학과",
      "학년": "3",
      "이수구분": "채플",
      "영역구분": "",
      "학점": "0",
      "교수명": "미지정",
      "수업시간/장소": "수3(미지정)",
      "수업시간": "수3",
      "장소": "미지정"
    },
    {
      "순번": "45",
      "강좌번호": "362",
      "과목코드": "1004424",
      "과목명": "전문실기III",
      "학부(과)": "생활체육학과",
      "학년": "4",
      "이수구분": "전공필수",
      "영역구분": "",
      "학점": "1",
      "교수명": "김갑수",
      "수업시간/장소": "월7~8(미지정)",
      "수업시간": "월7~8",
      "장소": "미지정"
    },
    {
      "순번": "46",
      "강좌번호": "365",
      "과목코드": "1000496",
      "과목명": "건강관리",
      "학부(과)": "생활체육학과",
      "학년": "4",
      "이수구분": "전공선택",
      "영역구분": "",
      "학점": "2",
      "교수명": "유광욱",
      "수업시간/장소": "목1~2(미지정)",
      "수업시간": "목1~2",
      "장소": "미지정"
    },
    {
      "순번": "47",
      "강좌번호": "1522",
      "과목코드": "1002612",
      "과목명": "스포츠 경제학",
      "학부(과)": "생활체육학과",
      "학년": "4",
      "이수구분": "전공선택",
      "영역구분": "",
      "학점": "2",
      "교수명": "조광현",
      "수업시간/장소": "수2~3(체육관107호(세미나실)-불가)",
      "수업시간": "수2~3",
      "장소": "체육관107호(세미나실)-불가"
    },
    {
      "순번": "48",
      "강좌번호": "367",
      "과목코드": "1002632",
      "과목명": "스포츠시설컨설팅",
      "학부(과)": "생활체육학과",
      "학년": "4",
      "이수구분": "전공선택",
      "영역구분": "",
      "학점": "2",
      "교수명": "홍계희",
      "수업시간/장소": "금3~4(미지정)",
      "수업시간": "금3~4",
      "장소": "미지정"
    },
    {
      "순번": "49",
      "강좌번호": "1612",
      "과목코드": "1002642",
      "과목명": "스포츠한의학",
      "학부(과)": "생활체육학과",
      "학년": "4",
      "이수구분": "전공선택",
      "영역구분": "",
      "학점": "2",
      "교수명": "이민영",
      "수업시간/장소": "화3~4(미지정)",
      "수업시간": "화3~4",
      "장소": "미지정"
    },
    {
      "순번": "50",
      "강좌번호": "366",
      "과목코드": "1002971",
      "과목명": "아동스포츠프로그램론",
      "학부(과)": "생활체육학과",
      "학년": "4",
      "이수구분": "전공선택",
      "영역구분": "",
      "학점": "2",
      "교수명": "박승순",
      "수업시간/장소": "화5~6(미지정)",
      "수업시간": "화5~6",
      "장소": "미지정"
    },
    {
      "순번": "51",
      "강좌번호": "368",
      "과목코드": "1003661",
      "과목명": "운동상해",
      "학부(과)": "생활체육학과",
      "학년": "4",
      "이수구분": "전공선택",
      "영역구분": "",
      "학점": "2",
      "교수명": "이애덕",
      "수업시간/장소": "월1~2(신학관103호강의실)",
      "수업시간": "월1~2",
      "장소": "신학관103호강의실"
    },
    {
      "순번": "52",
      "강좌번호": "1521",
      "과목코드": "1004982",
      "과목명": "체육정책과 법률",
      "학부(과)": "생활체육학과",
      "학년": "4",
      "이수구분": "전공선택",
      "영역구분": "",
      "학점": "2",
      "교수명": "한왕택",
      "수업시간/장소": "수5~6",
      "수업시간": "수5~6",
      "장소": ""
    },
    {
      "순번": "53",
      "강좌번호": "361",
      "과목코드": "1000833",
      "과목명": "교과교육론",
      "학부(과)": "생활체육학과",
      "학년": "4",
      "이수구분": "교직필수",
      "영역구분": "",
      "학점": "2",
      "교수명": "박승순",
      "수업시간/장소": "목5~6",
      "수업시간": "목5~6",
      "장소": ""
    },
    {
      "순번": "54",
      "강좌번호": "1279",
      "과목코드": "1004903",
      "과목명": "채플",
      "학부(과)": "생활체육학과",
      "학년": "4",
      "이수구분": "채플",
      "영역구분": "",
      "학점": "0",
      "교수명": "미지정",
      "수업시간/장소": "월3(미지정)",
      "수업시간": "월3",
      "장소": "미지정"
    }
  ]
}