{
  "api": [
    {
      "순번": "1",
      "강좌번호": "2384",
      "과목코드": "1004903",
      "과목명": "채플",
      "학부(과)": "경영학과",
      "학년": "1",
      "이수구분": "채플",
      "영역구분": "",
      "학점": "0",
      "교수명": "",
      "수업시간/장소": "",
      "수업시간": "",
      "장소": ""
    },
    {
      "순번": "2",
      "강좌번호": "2405",
      "과목코드": "1000332",
      "과목명": "TOEIC",
      "학부(과)": "경영학과",
      "학년": "1",
      "이수구분": "",
      "영역구분": "",
      "학점": "2",
      "교수명": "",
      "수업시간/장소": "",
      "수업시간": "",
      "장소": ""
    },
    {
      "순번": "3",
      "강좌번호": "2412",
      "과목코드": "1000620",
      "과목명": "경영통계론",
      "학부(과)": "경영학과",
      "학년": "1",
      "이수구분": "",
      "영역구분": "",
      "학점": "3",
      "교수명": "",
      "수업시간/장소": "",
      "수업시간": "",
      "장소": ""
    },
    {
      "순번": "4",
      "강좌번호": "2392",
      "과목코드": "1000904",
      "과목명": "교육학개론",
      "학부(과)": "경영학과",
      "학년": "1",
      "이수구분": "",
      "영역구분": "",
      "학점": "2",
      "교수명": "",
      "수업시간/장소": "",
      "수업시간": "",
      "장소": ""
    },
    {
      "순번": "5",
      "강좌번호": "2398",
      "과목코드": "1000995",
      "과목명": "국어 및 한문",
      "학부(과)": "경영학과",
      "학년": "1",
      "이수구분": "",
      "영역구분": "",
      "학점": "2",
      "교수명": "",
      "수업시간/장소": "",
      "수업시간": "",
      "장소": ""
    },
    {
      "순번": "6",
      "강좌번호": "2396",
      "과목코드": "1001109",
      "과목명": "기독교 사상(예수의 생애와 교훈)",
      "학부(과)": "경영학과",
      "학년": "1",
      "이수구분": "",
      "영역구분": "인성교양",
      "학점": "2",
      "교수명": "",
      "수업시간/장소": "",
      "수업시간": "",
      "장소": ""
    },
    {
      "순번": "7",
      "강좌번호": "2395",
      "과목코드": "1001135",
      "과목명": "종교와인생(구,기독교입문)",
      "학부(과)": "경영학과",
      "학년": "1",
      "이수구분": "",
      "영역구분": "인성교양",
      "학점": "2",
      "교수명": "",
      "수업시간/장소": "",
      "수업시간": "",
      "장소": ""
    },
    {
      "순번": "8",
      "강좌번호": "2397",
      "과목코드": "1001290",
      "과목명": "노작교육(그린교육)",
      "학부(과)": "경영학과",
      "학년": "1",
      "이수구분": "",
      "영역구분": "인성교양",
      "학점": "1",
      "교수명": "",
      "수업시간/장소": "",
      "수업시간": "",
      "장소": ""
    },
    {
      "순번": "9",
      "강좌번호": "2402",
      "과목코드": "1001378",
      "과목명": "대학수학",
      "학부(과)": "경영학과",
      "학년": "1",
      "이수구분": "",
      "영역구분": "",
      "학점": "3",
      "교수명": "",
      "수업시간/장소": "",
      "수업시간": "",
      "장소": ""
    },
    {
      "순번": "10",
      "강좌번호": "2394",
      "과목코드": "1003308",
      "과목명": "영상영어",
      "학부(과)": "경영학과",
      "학년": "1",
      "이수구분": "",
      "영역구분": "",
      "학점": "3",
      "교수명": "",
      "수업시간/장소": "",
      "수업시간": "",
      "장소": ""
    },
    {
      "순번": "11",
      "강좌번호": "2393",
      "과목코드": "1003400",
      "과목명": "영어기초",
      "학부(과)": "경영학과",
      "학년": "1",
      "이수구분": "",
      "영역구분": "",
      "학점": "3",
      "교수명": "",
      "수업시간/장소": "",
      "수업시간": "",
      "장소": ""
    },
    {
      "순번": "12",
      "강좌번호": "2399",
      "과목코드": "1003502",
      "과목명": "영어회화 및 독해 I",
      "학부(과)": "경영학과",
      "학년": "1",
      "이수구분": "",
      "영역구분": "",
      "학점": "3",
      "교수명": "",
      "수업시간/장소": "",
      "수업시간": "",
      "장소": ""
    },
    {
      "순번": "13",
      "강좌번호": "2403",
      "과목코드": "1003915",
      "과목명": "음악감상법I",
      "학부(과)": "경영학과",
      "학년": "1",
      "이수구분": "",
      "영역구분": "",
      "학점": "2",
      "교수명": "",
      "수업시간/장소": "",
      "수업시간": "",
      "장소": ""
    },
    {
      "순번": "14",
      "강좌번호": "2413",
      "과목코드": "1003995",
      "과목명": "의사결정론",
      "학부(과)": "경영학과",
      "학년": "1",
      "이수구분": "",
      "영역구분": "",
      "학점": "3",
      "교수명": "",
      "수업시간/장소": "",
      "수업시간": "",
      "장소": ""
    },
    {
      "순번": "15",
      "강좌번호": "2386",
      "과목코드": "1004128",
      "과목명": "일반생물학 I",
      "학부(과)": "경영학과",
      "학년": "1",
      "이수구분": "",
      "영역구분": "",
      "학점": "3",
      "교수명": "",
      "수업시간/장소": "",
      "수업시간": "",
      "장소": ""
    },
    {
      "순번": "16",
      "강좌번호": "2387",
      "과목코드": "1004134",
      "과목명": "일반생물학 실험",
      "학부(과)": "경영학과",
      "학년": "1",
      "이수구분": "",
      "영역구분": "",
      "학점": "1",
      "교수명": "",
      "수업시간/장소": "",
      "수업시간": "",
      "장소": ""
    },
    {
      "순번": "17",
      "강좌번호": "2388",
      "과목코드": "1004152",
      "과목명": "일반화학 I",
      "학부(과)": "경영학과",
      "학년": "1",
      "이수구분": "",
      "영역구분": "",
      "학점": "3",
      "교수명": "",
      "수업시간/장소": "",
      "수업시간": "",
      "장소": ""
    },
    {
      "순번": "18",
      "강좌번호": "2389",
      "과목코드": "1004159",
      "과목명": "일반화학실험",
      "학부(과)": "경영학과",
      "학년": "1",
      "이수구분": "",
      "영역구분": "",
      "학점": "1",
      "교수명": "",
      "수업시간/장소": "",
      "수업시간": "",
      "장소": ""
    },
    {
      "순번": "19",
      "강좌번호": "2411",
      "과목코드": "1004355",
      "과목명": "재무관리",
      "학부(과)": "경영학과",
      "학년": "1",
      "이수구분": "",
      "영역구분": "",
      "학점": "3",
      "교수명": "",
      "수업시간/장소": "",
      "수업시간": "",
      "장소": ""
    },
    {
      "순번": "20",
      "강좌번호": "2409",
      "과목코드": "1004794",
      "과목명": "증권시장론",
      "학부(과)": "경영학과",
      "학년": "1",
      "이수구분": "",
      "영역구분": "",
      "학점": "3",
      "교수명": "",
      "수업시간/장소": "",
      "수업시간": "",
      "장소": ""
    },
    {
      "순번": "21",
      "강좌번호": "2385",
      "과목코드": "1004933",
      "과목명": "청소년 이해와 상담",
      "학부(과)": "경영학과",
      "학년": "1",
      "이수구분": "",
      "영역구분": "",
      "학점": "2",
      "교수명": "",
      "수업시간/장소": "",
      "수업시간": "",
      "장소": ""
    },
    {
      "순번": "22",
      "강좌번호": "2404",
      "과목코드": "1004946",
      "과목명": "체육",
      "학부(과)": "경영학과",
      "학년": "1",
      "이수구분": "",
      "영역구분": "",
      "학점": "1",
      "교수명": "",
      "수업시간/장소": "",
      "수업시간": "",
      "장소": ""
    },
    {
      "순번": "23",
      "강좌번호": "2400",
      "과목코드": "1005013",
      "과목명": "초급영어어휘",
      "학부(과)": "경영학과",
      "학년": "1",
      "이수구분": "",
      "영역구분": "",
      "학점": "2",
      "교수명": "",
      "수업시간/장소": "",
      "수업시간": "",
      "장소": ""
    },
    {
      "순번": "24",
      "강좌번호": "2390",
      "과목코드": "1005099",
      "과목명": "컴퓨터 활용I",
      "학부(과)": "경영학과",
      "학년": "1",
      "이수구분": "",
      "영역구분": "컴퓨터활용",
      "학점": "2",
      "교수명": "",
      "수업시간/장소": "",
      "수업시간": "",
      "장소": ""
    },
    {
      "순번": "25",
      "강좌번호": "2391",
      "과목코드": "1005141",
      "과목명": "컴퓨터의 이해",
      "학부(과)": "경영학과",
      "학년": "1",
      "이수구분": "",
      "영역구분": "",
      "학점": "3",
      "교수명": "",
      "수업시간/장소": "",
      "수업시간": "",
      "장소": ""
    },
    {
      "순번": "26",
      "강좌번호": "2410",
      "과목코드": "1005395",
      "과목명": "한국경제론",
      "학부(과)": "경영학과",
      "학년": "1",
      "이수구분": "",
      "영역구분": "",
      "학점": "3",
      "교수명": "",
      "수업시간/장소": "",
      "수업시간": "",
      "장소": ""
    },
    {
      "순번": "27",
      "강좌번호": "2407",
      "과목코드": "1005567",
      "과목명": "현대경영의 이해",
      "학부(과)": "경영학과",
      "학년": "1",
      "이수구분": "",
      "영역구분": "",
      "학점": "3",
      "교수명": "",
      "수업시간/장소": "",
      "수업시간": "",
      "장소": ""
    },
    {
      "순번": "28",
      "강좌번호": "2406",
      "과목코드": "1005585",
      "과목명": "현대사회와 광고",
      "학부(과)": "경영학과",
      "학년": "1",
      "이수구분": "",
      "영역구분": "",
      "학점": "2",
      "교수명": "",
      "수업시간/장소": "",
      "수업시간": "",
      "장소": ""
    },
    {
      "순번": "29",
      "강좌번호": "2401",
      "과목코드": "1005638",
      "과목명": "현실경제의 이해",
      "학부(과)": "경영학과",
      "학년": "1",
      "이수구분": "",
      "영역구분": "",
      "학점": "2",
      "교수명": "",
      "수업시간/장소": "",
      "수업시간": "",
      "장소": ""
    },
    {
      "순번": "30",
      "강좌번호": "2408",
      "과목코드": "1005784",
      "과목명": "회계원리",
      "학부(과)": "경영학과",
      "학년": "1",
      "이수구분": "",
      "영역구분": "",
      "학점": "3",
      "교수명": "",
      "수업시간/장소": "",
      "수업시간": "",
      "장소": ""
    },
    {
      "순번": "31",
      "강좌번호": "535",
      "과목코드": "1001109",
      "과목명": "기독교 사상(예수의 생애와 교훈)",
      "학부(과)": "경영학과",
      "학년": "2",
      "이수구분": "교양필수",
      "영역구분": "인성교양",
      "학점": "2",
      "교수명": "송호철",
      "수업시간/장소": "목5~6(사무엘관208호강의실)",
      "수업시간": "목5~6",
      "장소": "사무엘관208호강의실"
    },
    {
      "순번": "32",
      "강좌번호": "543",
      "과목코드": "1000620",
      "과목명": "경영통계론",
      "학부(과)": "경영학과",
      "학년": "2",
      "이수구분": "전공기초",
      "영역구분": "",
      "학점": "3",
      "교수명": "유한주",
      "수업시간/장소": "월6(사무엘관210호(PBL소형)강의실),목2~3(사무엘관210호(PBL소형)강의실)",
      "수업시간": "월6,목2~3",
      "장소": "사무엘관210호(PBL소형)강의실"
    },
    {
      "순번": "33",
      "강좌번호": "544",
      "과목코드": "1005784",
      "과목명": "회계원리",
      "학부(과)": "경영학과",
      "학년": "2",
      "이수구분": "전공필수",
      "영역구분": "",
      "학점": "3",
      "교수명": "최준환",
      "수업시간/장소": "월3(미지정),수3~4(미지정)",
      "수업시간": "월3,수3~4",
      "장소": "미지정"
    },
    {
      "순번": "34",
      "강좌번호": "547",
      "과목코드": "1004794",
      "과목명": "증권시장론",
      "학부(과)": "경영학과",
      "학년": "2",
      "이수구분": "전공선택",
      "영역구분": "",
      "학점": "3",
      "교수명": "고종문",
      "수업시간/장소": "금5~7(사무엘관202호강의실)",
      "수업시간": "금5~7",
      "장소": "사무엘관202호강의실"
    },
    {
      "순번": "35",
      "강좌번호": "546",
      "과목코드": "1005395",
      "과목명": "한국경제론",
      "학부(과)": "경영학과",
      "학년": "2",
      "이수구분": "전공선택",
      "영역구분": "",
      "학점": "3",
      "교수명": "권혁용",
      "수업시간/장소": "화2(사무엘관202호강의실),금2~3(사무엘관202호강의실)",
      "수업시간": "화2,금2~3",
      "장소": "사무엘관202호강의실"
    },
    {
      "순번": "36",
      "강좌번호": "549",
      "과목코드": "1000885",
      "과목명": "교육사회학",
      "학부(과)": "경영학과",
      "학년": "2",
      "이수구분": "교직필수",
      "영역구분": "",
      "학점": "2",
      "교수명": "최수동",
      "수업시간/장소": "화3~4(미지정)",
      "수업시간": "화3~4",
      "장소": "미지정"
    },
    {
      "순번": "37",
      "강좌번호": "548",
      "과목코드": "1000904",
      "과목명": "교육학개론",
      "학부(과)": "경영학과",
      "학년": "2",
      "이수구분": "교직필수",
      "영역구분": "",
      "학점": "2",
      "교수명": "조영일",
      "수업시간/장소": "화6~7(미지정)",
      "수업시간": "화6~7",
      "장소": "미지정"
    },
    {
      "순번": "38",
      "강좌번호": "2414",
      "과목코드": "1004903",
      "과목명": "채플",
      "학부(과)": "경영학과",
      "학년": "2",
      "이수구분": "채플",
      "영역구분": "",
      "학점": "0",
      "교수명": "",
      "수업시간/장소": "",
      "수업시간": "",
      "장소": ""
    },
    {
      "순번": "39",
      "강좌번호": "2448",
      "과목코드": "1000013",
      "과목명": "19C 낭만주의 영시",
      "학부(과)": "경영학과",
      "학년": "2",
      "이수구분": "",
      "영역구분": "",
      "학점": "3",
      "교수명": "",
      "수업시간/장소": "",
      "수업시간": "",
      "장소": ""
    },
    {
      "순번": "40",
      "강좌번호": "2439",
      "과목코드": "1000330",
      "과목명": "TOEFL",
      "학부(과)": "경영학과",
      "학년": "2",
      "이수구분": "",
      "영역구분": "",
      "학점": "2",
      "교수명": "",
      "수업시간/장소": "",
      "수업시간": "",
      "장소": ""
    },
    {
      "순번": "41",
      "강좌번호": "2440",
      "과목코드": "1000332",
      "과목명": "TOEIC",
      "학부(과)": "경영학과",
      "학년": "2",
      "이수구분": "",
      "영역구분": "",
      "학점": "2",
      "교수명": "",
      "수업시간/장소": "",
      "수업시간": "",
      "장소": ""
    },
    {
      "순번": "42",
      "강좌번호": "2445",
      "과목코드": "1000416",
      "과목명": "가정제과 제빵",
      "학부(과)": "경영학과",
      "학년": "2",
      "이수구분": "",
      "영역구분": "",
      "학점": "2",
      "교수명": "",
      "수업시간/장소": "",
      "수업시간": "",
      "장소": ""
    },
    {
      "순번": "43",
      "강좌번호": "2416",
      "과목코드": "1000583",
      "과목명": "결혼과 가족관계",
      "학부(과)": "경영학과",
      "학년": "2",
      "이수구분": "",
      "영역구분": "인성교양",
      "학점": "2",
      "교수명": "",
      "수업시간/장소": "",
      "수업시간": "",
      "장소": ""
    },
    {
      "순번": "44",
      "강좌번호": "2417",
      "과목코드": "1000930",
      "과목명": "교회음악",
      "학부(과)": "경영학과",
      "학년": "2",
      "이수구분": "",
      "영역구분": "",
      "학점": "2",
      "교수명": "",
      "수업시간/장소": "",
      "수업시간": "",
      "장소": ""
    },
    {
      "순번": "45",
      "강좌번호": "2427",
      "과목코드": "1000995",
      "과목명": "국어 및 한문",
      "학부(과)": "경영학과",
      "학년": "2",
      "이수구분": "",
      "영역구분": "",
      "학점": "2",
      "교수명": "",
      "수업시간/장소": "",
      "수업시간": "",
      "장소": ""
    },
    {
      "순번": "46",
      "강좌번호": "2424",
      "과목코드": "1001211",
      "과목명": "기초영양학",
      "학부(과)": "경영학과",
      "학년": "2",
      "이수구분": "",
      "영역구분": "",
      "학점": "3",
      "교수명": "",
      "수업시간/장소": "",
      "수업시간": "",
      "장소": ""
    },
    {
      "순번": "47",
      "강좌번호": "2442",
      "과목코드": "1001619",
      "과목명": "매스컴의 이해",
      "학부(과)": "경영학과",
      "학년": "2",
      "이수구분": "",
      "영역구분": "",
      "학점": "2",
      "교수명": "",
      "수업시간/장소": "",
      "수업시간": "",
      "장소": ""
    },
    {
      "순번": "48",
      "강좌번호": "2447",
      "과목코드": "1001622",
      "과목명": "멀티미디어",
      "학부(과)": "경영학과",
      "학년": "2",
      "이수구분": "",
      "영역구분": "",
      "학점": "3",
      "교수명": "",
      "수업시간/장소": "",
      "수업시간": "",
      "장소": ""
    },
    {
      "순번": "49",
      "강좌번호": "2443",
      "과목코드": "1002162",
      "과목명": "사회봉사I",
      "학부(과)": "경영학과",
      "학년": "2",
      "이수구분": "",
      "영역구분": "",
      "학점": "2",
      "교수명": "",
      "수업시간/장소": "",
      "수업시간": "",
      "장소": ""
    },
    {
      "순번": "50",
      "강좌번호": "2451",
      "과목코드": "1002253",
      "과목명": "생산관리",
      "학부(과)": "경영학과",
      "학년": "2",
      "이수구분": "",
      "영역구분": "",
      "학점": "3",
      "교수명": "",
      "수업시간/장소": "",
      "수업시간": "",
      "장소": ""
    },
    {
      "순번": "51",
      "강좌번호": "2435",
      "과목코드": "1002286",
      "과목명": "생활과학",
      "학부(과)": "경영학과",
      "학년": "2",
      "이수구분": "",
      "영역구분": "",
      "학점": "2",
      "교수명": "",
      "수업시간/장소": "",
      "수업시간": "",
      "장소": ""
    },
    {
      "순번": "52",
      "강좌번호": "2436",
      "과목코드": "1002310",
      "과목명": "생활원예",
      "학부(과)": "경영학과",
      "학년": "2",
      "이수구분": "",
      "영역구분": "",
      "학점": "2",
      "교수명": "",
      "수업시간/장소": "",
      "수업시간": "",
      "장소": ""
    },
    {
      "순번": "53",
      "강좌번호": "2415",
      "과목코드": "1002446",
      "과목명": "성소론",
      "학부(과)": "경영학과",
      "학년": "2",
      "이수구분": "",
      "영역구분": "인성교양",
      "학점": "2",
      "교수명": "",
      "수업시간/장소": "",
      "수업시간": "",
      "장소": ""
    },
    {
      "순번": "54",
      "강좌번호": "2452",
      "과목코드": "1002538",
      "과목명": "소비자행동론",
      "학부(과)": "경영학과",
      "학년": "2",
      "이수구분": "",
      "영역구분": "",
      "학점": "3",
      "교수명": "",
      "수업시간/장소": "",
      "수업시간": "",
      "장소": ""
    },
    {
      "순번": "55",
      "강좌번호": "2432",
      "과목코드": "1002582",
      "과목명": "수학의 이해",
      "학부(과)": "경영학과",
      "학년": "2",
      "이수구분": "",
      "영역구분": "",
      "학점": "2",
      "교수명": "",
      "수업시간/장소": "",
      "수업시간": "",
      "장소": ""
    },
    {
      "순번": "56",
      "강좌번호": "2425",
      "과목코드": "1002761",
      "과목명": "식품학",
      "학부(과)": "경영학과",
      "학년": "2",
      "이수구분": "",
      "영역구분": "",
      "학점": "3",
      "교수명": "",
      "수업시간/장소": "",
      "수업시간": "",
      "장소": ""
    },
    {
      "순번": "57",
      "강좌번호": "2428",
      "과목코드": "1003252",
      "과목명": "영문법(초급)",
      "학부(과)": "경영학과",
      "학년": "2",
      "이수구분": "",
      "영역구분": "",
      "학점": "2",
      "교수명": "",
      "수업시간/장소": "",
      "수업시간": "",
      "장소": ""
    },
    {
      "순번": "58",
      "강좌번호": "2449",
      "과목코드": "1003294",
      "과목명": "영미수필",
      "학부(과)": "경영학과",
      "학년": "2",
      "이수구분": "",
      "영역구분": "",
      "학점": "3",
      "교수명": "",
      "수업시간/장소": "",
      "수업시간": "",
      "장소": ""
    },
    {
      "순번": "59",
      "강좌번호": "2433",
      "과목코드": "1003335",
      "과목명": "영양과 건강관리",
      "학부(과)": "경영학과",
      "학년": "2",
      "이수구분": "",
      "영역구분": "",
      "학점": "2",
      "교수명": "",
      "수업시간/장소": "",
      "수업시간": "",
      "장소": ""
    },
    {
      "순번": "60",
      "강좌번호": "2422",
      "과목코드": "1003462",
      "과목명": "영어읽기 및 듣기II",
      "학부(과)": "경영학과",
      "학년": "2",
      "이수구분": "",
      "영역구분": "",
      "학점": "3",
      "교수명": "",
      "수업시간/장소": "",
      "수업시간": "",
      "장소": ""
    },
    {
      "순번": "61",
      "강좌번호": "2423",
      "과목코드": "1003504",
      "과목명": "영어회화 및 작문",
      "학부(과)": "경영학과",
      "학년": "2",
      "이수구분": "",
      "영역구분": "",
      "학점": "2",
      "교수명": "",
      "수업시간/장소": "",
      "수업시간": "",
      "장소": ""
    },
    {
      "순번": "62",
      "강좌번호": "2438",
      "과목코드": "1003915",
      "과목명": "음악감상법I",
      "학부(과)": "경영학과",
      "학년": "2",
      "이수구분": "",
      "영역구분": "",
      "학점": "2",
      "교수명": "",
      "수업시간/장소": "",
      "수업시간": "",
      "장소": ""
    },
    {
      "순번": "63",
      "강좌번호": "2455",
      "과목코드": "1003995",
      "과목명": "의사결정론",
      "학부(과)": "경영학과",
      "학년": "2",
      "이수구분": "",
      "영역구분": "",
      "학점": "3",
      "교수명": "",
      "수업시간/장소": "",
      "수업시간": "",
      "장소": ""
    },
    {
      "순번": "64",
      "강좌번호": "2431",
      "과목코드": "1004033",
      "과목명": "인간관계론",
      "학부(과)": "경영학과",
      "학년": "2",
      "이수구분": "",
      "영역구분": "",
      "학점": "2",
      "교수명": "",
      "수업시간/장소": "",
      "수업시간": "",
      "장소": ""
    },
    {
      "순번": "65",
      "강좌번호": "2430",
      "과목코드": "1004143",
      "과목명": "일반심리학",
      "학부(과)": "경영학과",
      "학년": "2",
      "이수구분": "",
      "영역구분": "",
      "학점": "2",
      "교수명": "",
      "수업시간/장소": "",
      "수업시간": "",
      "장소": ""
    },
    {
      "순번": "66",
      "강좌번호": "2453",
      "과목코드": "1004355",
      "과목명": "재무관리",
      "학부(과)": "경영학과",
      "학년": "2",
      "이수구분": "",
      "영역구분": "",
      "학점": "3",
      "교수명": "",
      "수업시간/장소": "",
      "수업시간": "",
      "장소": ""
    },
    {
      "순번": "67",
      "강좌번호": "2426",
      "과목코드": "1004544",
      "과목명": "조리원리",
      "학부(과)": "경영학과",
      "학년": "2",
      "이수구분": "",
      "영역구분": "",
      "학점": "3",
      "교수명": "",
      "수업시간/장소": "",
      "수업시간": "",
      "장소": ""
    },
    {
      "순번": "68",
      "강좌번호": "2454",
      "과목코드": "1004763",
      "과목명": "중급회계",
      "학부(과)": "경영학과",
      "학년": "2",
      "이수구분": "",
      "영역구분": "",
      "학점": "3",
      "교수명": "",
      "수업시간/장소": "",
      "수업시간": "",
      "장소": ""
    },
    {
      "순번": "69",
      "강좌번호": "2446",
      "과목코드": "1004872",
      "과목명": "창업실무",
      "학부(과)": "경영학과",
      "학년": "2",
      "이수구분": "",
      "영역구분": "",
      "학점": "2",
      "교수명": "",
      "수업시간/장소": "",
      "수업시간": "",
      "장소": ""
    },
    {
      "순번": "70",
      "강좌번호": "2434",
      "과목코드": "1004914",
      "과목명": "천연치료법",
      "학부(과)": "경영학과",
      "학년": "2",
      "이수구분": "",
      "영역구분": "",
      "학점": "2",
      "교수명": "",
      "수업시간/장소": "",
      "수업시간": "",
      "장소": ""
    },
    {
      "순번": "71",
      "강좌번호": "2419",
      "과목코드": "1004933",
      "과목명": "청소년 이해와 상담",
      "학부(과)": "경영학과",
      "학년": "2",
      "이수구분": "",
      "영역구분": "",
      "학점": "2",
      "교수명": "",
      "수업시간/장소": "",
      "수업시간": "",
      "장소": ""
    },
    {
      "순번": "72",
      "강좌번호": "2418",
      "과목코드": "1004944",
      "과목명": "청소년지도법",
      "학부(과)": "경영학과",
      "학년": "2",
      "이수구분": "",
      "영역구분": "인성교양",
      "학점": "2",
      "교수명": "",
      "수업시간/장소": "",
      "수업시간": "",
      "장소": ""
    },
    {
      "순번": "73",
      "강좌번호": "2420",
      "과목코드": "1005099",
      "과목명": "컴퓨터 활용I",
      "학부(과)": "경영학과",
      "학년": "2",
      "이수구분": "",
      "영역구분": "컴퓨터활용",
      "학점": "2",
      "교수명": "",
      "수업시간/장소": "",
      "수업시간": "",
      "장소": ""
    },
    {
      "순번": "74",
      "강좌번호": "2421",
      "과목코드": "1005141",
      "과목명": "컴퓨터의 이해",
      "학부(과)": "경영학과",
      "학년": "2",
      "이수구분": "",
      "영역구분": "",
      "학점": "3",
      "교수명": "",
      "수업시간/장소": "",
      "수업시간": "",
      "장소": ""
    },
    {
      "순번": "75",
      "강좌번호": "2437",
      "과목코드": "1005487",
      "과목명": "합창 I",
      "학부(과)": "경영학과",
      "학년": "2",
      "이수구분": "",
      "영역구분": "",
      "학점": "2",
      "교수명": "",
      "수업시간/장소": "",
      "수업시간": "",
      "장소": ""
    },
    {
      "순번": "76",
      "강좌번호": "2450",
      "과목코드": "1005567",
      "과목명": "현대경영의 이해",
      "학부(과)": "경영학과",
      "학년": "2",
      "이수구분": "",
      "영역구분": "",
      "학점": "3",
      "교수명": "",
      "수업시간/장소": "",
      "수업시간": "",
      "장소": ""
    },
    {
      "순번": "77",
      "강좌번호": "2441",
      "과목코드": "1005585",
      "과목명": "현대사회와 광고",
      "학부(과)": "경영학과",
      "학년": "2",
      "이수구분": "",
      "영역구분": "",
      "학점": "2",
      "교수명": "",
      "수업시간/장소": "",
      "수업시간": "",
      "장소": ""
    },
    {
      "순번": "78",
      "강좌번호": "2429",
      "과목코드": "1005638",
      "과목명": "현실경제의 이해",
      "학부(과)": "경영학과",
      "학년": "2",
      "이수구분": "",
      "영역구분": "",
      "학점": "2",
      "교수명": "",
      "수업시간/장소": "",
      "수업시간": "",
      "장소": ""
    },
    {
      "순번": "79",
      "강좌번호": "2444",
      "과목코드": "1005755",
      "과목명": "환경미학",
      "학부(과)": "경영학과",
      "학년": "2",
      "이수구분": "",
      "영역구분": "",
      "학점": "2",
      "교수명": "",
      "수업시간/장소": "",
      "수업시간": "",
      "장소": ""
    },
    {
      "순번": "80",
      "강좌번호": "827",
      "과목코드": "1000606",
      "과목명": "경영영어 II",
      "학부(과)": "경영학과",
      "학년": "3",
      "이수구분": "전공필수",
      "영역구분": "",
      "학점": "1",
      "교수명": "박은숙",
      "수업시간/장소": "목8~9(사무엘관201호강의실)",
      "수업시간": "목8~9",
      "장소": "사무엘관201호강의실"
    },
    {
      "순번": "81",
      "강좌번호": "607",
      "과목코드": "1000606",
      "과목명": "경영영어 II",
      "학부(과)": "경영학과",
      "학년": "3",
      "이수구분": "전공필수",
      "영역구분": "",
      "학점": "1",
      "교수명": "박은숙",
      "수업시간/장소": "화8~9(사무엘관208호강의실)",
      "수업시간": "화8~9",
      "장소": "사무엘관208호강의실"
    },
    {
      "순번": "82",
      "강좌번호": "604",
      "과목코드": "1002253",
      "과목명": "생산관리",
      "학부(과)": "경영학과",
      "학년": "3",
      "이수구분": "전공필수",
      "영역구분": "",
      "학점": "3",
      "교수명": "유한주",
      "수업시간/장소": "월3~4(사무엘관202호강의실),목7(사무엘관202호강의실)",
      "수업시간": "월3~4,목7",
      "장소": "사무엘관202호강의실"
    },
    {
      "순번": "83",
      "강좌번호": "606",
      "과목코드": "1004355",
      "과목명": "재무관리",
      "학부(과)": "경영학과",
      "학년": "3",
      "이수구분": "전공필수",
      "영역구분": "",
      "학점": "3",
      "교수명": "고종문",
      "수업시간/장소": "금1~3(바울관403호강의실)",
      "수업시간": "금1~3",
      "장소": "바울관403호강의실"
    },
    {
      "순번": "84",
      "강좌번호": "605",
      "과목코드": "1002538",
      "과목명": "소비자행동론",
      "학부(과)": "경영학과",
      "학년": "3",
      "이수구분": "전공선택",
      "영역구분": "",
      "학점": "3",
      "교수명": "김광규",
      "수업시간/장소": "월8(사무엘관208호강의실),수3~4(사무엘관208호강의실)",
      "수업시간": "월8,수3~4",
      "장소": "사무엘관208호강의실"
    },
    {
      "순번": "85",
      "강좌번호": "608",
      "과목코드": "1003995",
      "과목명": "의사결정론",
      "학부(과)": "경영학과",
      "학년": "3",
      "이수구분": "전공선택",
      "영역구분": "",
      "학점": "3",
      "교수명": "정태석",
      "수업시간/장소": "수6~8(사무엘관208호강의실)",
      "수업시간": "수6~8",
      "장소": "사무엘관208호강의실"
    },
    {
      "순번": "86",
      "강좌번호": "602",
      "과목코드": "1000833",
      "과목명": "교과교육론",
      "학부(과)": "경영학과",
      "학년": "3",
      "이수구분": "교직필수",
      "영역구분": "",
      "학점": "2",
      "교수명": "권혁용",
      "수업시간/장소": "",
      "수업시간": "",
      "장소": ""
    },
    {
      "순번": "87",
      "강좌번호": "601",
      "과목코드": "1000904",
      "과목명": "교육학개론",
      "학부(과)": "경영학과",
      "학년": "3",
      "이수구분": "교직필수",
      "영역구분": "",
      "학점": "2",
      "교수명": "조영일",
      "수업시간/장소": "목5~6(미지정)",
      "수업시간": "목5~6",
      "장소": "미지정"
    },
    {
      "순번": "88",
      "강좌번호": "2456",
      "과목코드": "1004903",
      "과목명": "채플",
      "학부(과)": "경영학과",
      "학년": "3",
      "이수구분": "채플",
      "영역구분": "",
      "학점": "0",
      "교수명": "",
      "수업시간/장소": "",
      "수업시간": "",
      "장소": ""
    },
    {
      "순번": "89",
      "강좌번호": "2458",
      "과목코드": "1000159",
      "과목명": "English Bible Reading I",
      "학부(과)": "경영학과",
      "학년": "3",
      "이수구분": "",
      "영역구분": "",
      "학점": "2",
      "교수명": "",
      "수업시간/장소": "",
      "수업시간": "",
      "장소": ""
    },
    {
      "순번": "90",
      "강좌번호": "2484",
      "과목코드": "1000410",
      "과목명": "가정보건",
      "학부(과)": "경영학과",
      "학년": "3",
      "이수구분": "",
      "영역구분": "",
      "학점": "2",
      "교수명": "",
      "수업시간/장소": "",
      "수업시간": "",
      "장소": ""
    },
    {
      "순번": "91",
      "강좌번호": "2498",
      "과목코드": "1000416",
      "과목명": "가정제과 제빵",
      "학부(과)": "경영학과",
      "학년": "3",
      "이수구분": "",
      "영역구분": "",
      "학점": "2",
      "교수명": "",
      "수업시간/장소": "",
      "수업시간": "",
      "장소": ""
    },
    {
      "순번": "92",
      "강좌번호": "2465",
      "과목코드": "1000583",
      "과목명": "결혼과 가족관계",
      "학부(과)": "경영학과",
      "학년": "3",
      "이수구분": "",
      "영역구분": "인성교양",
      "학점": "2",
      "교수명": "",
      "수업시간/장소": "",
      "수업시간": "",
      "장소": ""
    },
    {
      "순번": "93",
      "강좌번호": "2500",
      "과목코드": "1000617",
      "과목명": "경영정보원론",
      "학부(과)": "경영학과",
      "학년": "3",
      "이수구분": "",
      "영역구분": "",
      "학점": "3",
      "교수명": "",
      "수업시간/장소": "",
      "수업시간": "",
      "장소": ""
    },
    {
      "순번": "94",
      "강좌번호": "2507",
      "과목코드": "1000620",
      "과목명": "경영통계론",
      "학부(과)": "경영학과",
      "학년": "3",
      "이수구분": "",
      "영역구분": "",
      "학점": "3",
      "교수명": "",
      "수업시간/장소": "",
      "수업시간": "",
      "장소": ""
    },
    {
      "순번": "95",
      "강좌번호": "2512",
      "과목코드": "1000640",
      "과목명": "경제학연습",
      "학부(과)": "경영학과",
      "학년": "3",
      "이수구분": "",
      "영역구분": "",
      "학점": "3",
      "교수명": "",
      "수업시간/장소": "",
      "수업시간": "",
      "장소": ""
    },
    {
      "순번": "96",
      "강좌번호": "2483",
      "과목코드": "1000757",
      "과목명": "공중보건",
      "학부(과)": "경영학과",
      "학년": "3",
      "이수구분": "",
      "영역구분": "",
      "학점": "2",
      "교수명": "",
      "수업시간/장소": "",
      "수업시간": "",
      "장소": ""
    },
    {
      "순번": "97",
      "강좌번호": "2470",
      "과목코드": "1000840",
      "과목명": "교내선교(Campus Ministry)",
      "학부(과)": "경영학과",
      "학년": "3",
      "이수구분": "",
      "영역구분": "",
      "학점": "2",
      "교수명": "",
      "수업시간/장소": "",
      "수업시간": "",
      "장소": ""
    },
    {
      "순번": "98",
      "강좌번호": "2477",
      "과목코드": "1000885",
      "과목명": "교육사회학",
      "학부(과)": "경영학과",
      "학년": "3",
      "이수구분": "",
      "영역구분": "",
      "학점": "2",
      "교수명": "",
      "수업시간/장소": "",
      "수업시간": "",
      "장소": ""
    },
    {
      "순번": "99",
      "강좌번호": "2462",
      "과목코드": "1000925",
      "과목명": "교회와 신앙활동",
      "학부(과)": "경영학과",
      "학년": "3",
      "이수구분": "",
      "영역구분": "",
      "학점": "2",
      "교수명": "",
      "수업시간/장소": "",
      "수업시간": "",
      "장소": ""
    },
    {
      "순번": "100",
      "강좌번호": "2478",
      "과목코드": "1000995",
      "과목명": "국어 및 한문",
      "학부(과)": "경영학과",
      "학년": "3",
      "이수구분": "",
      "영역구분": "",
      "학점": "2",
      "교수명": "",
      "수업시간/장소": "",
      "수업시간": "",
      "장소": ""
    },
    {
      "순번": "101",
      "강좌번호": "2510",
      "과목코드": "1001003",
      "과목명": "국제경영학",
      "학부(과)": "경영학과",
      "학년": "3",
      "이수구분": "",
      "영역구분": "",
      "학점": "3",
      "교수명": "",
      "수업시간/장소": "",
      "수업시간": "",
      "장소": ""
    },
    {
      "순번": "102",
      "강좌번호": "2461",
      "과목코드": "1001024",
      "과목명": "그리스도인 생활과 윤리",
      "학부(과)": "경영학과",
      "학년": "3",
      "이수구분": "",
      "영역구분": "인성교양",
      "학점": "2",
      "교수명": "",
      "수업시간/장소": "",
      "수업시간": "",
      "장소": ""
    },
    {
      "순번": "103",
      "강좌번호": "2463",
      "과목코드": "1001030",
      "과목명": "그리스도인 화법",
      "학부(과)": "경영학과",
      "학년": "3",
      "이수구분": "",
      "영역구분": "인성교양",
      "학점": "2",
      "교수명": "",
      "수업시간/장소": "",
      "수업시간": "",
      "장소": ""
    },
    {
      "순번": "104",
      "강좌번호": "2475",
      "과목코드": "1001406",
      "과목명": "데이터통신개론",
      "학부(과)": "경영학과",
      "학년": "3",
      "이수구분": "",
      "영역구분": "",
      "학점": "3",
      "교수명": "",
      "수업시간/장소": "",
      "수업시간": "",
      "장소": ""
    },
    {
      "순번": "105",
      "강좌번호": "2457",
      "과목코드": "1001572",
      "과목명": "로마서",
      "학부(과)": "경영학과",
      "학년": "3",
      "이수구분": "",
      "영역구분": "인성교양",
      "학점": "2",
      "교수명": "",
      "수업시간/장소": "",
      "수업시간": "",
      "장소": ""
    },
    {
      "순번": "106",
      "강좌번호": "2493",
      "과목코드": "1001619",
      "과목명": "매스컴의 이해",
      "학부(과)": "경영학과",
      "학년": "3",
      "이수구분": "",
      "영역구분": "",
      "학점": "2",
      "교수명": "",
      "수업시간/장소": "",
      "수업시간": "",
      "장소": ""
    },
    {
      "순번": "107",
      "강좌번호": "2497",
      "과목코드": "1001989",
      "과목명": "볼링",
      "학부(과)": "경영학과",
      "학년": "3",
      "이수구분": "",
      "영역구분": "",
      "학점": "1",
      "교수명": "",
      "수업시간/장소": "",
      "수업시간": "",
      "장소": ""
    },
    {
      "순번": "108",
      "강좌번호": "2490",
      "과목코드": "1002109",
      "과목명": "사진촬영",
      "학부(과)": "경영학과",
      "학년": "3",
      "이수구분": "",
      "영역구분": "",
      "학점": "2",
      "교수명": "",
      "수업시간/장소": "",
      "수업시간": "",
      "장소": ""
    },
    {
      "순번": "109",
      "강좌번호": "2494",
      "과목코드": "1002162",
      "과목명": "사회봉사I",
      "학부(과)": "경영학과",
      "학년": "3",
      "이수구분": "",
      "영역구분": "",
      "학점": "2",
      "교수명": "",
      "수업시간/장소": "",
      "수업시간": "",
      "장소": ""
    },
    {
      "순번": "110",
      "강좌번호": "2480",
      "과목코드": "1002175",
      "과목명": "사회학",
      "학부(과)": "경영학과",
      "학년": "3",
      "이수구분": "",
      "영역구분": "",
      "학점": "2",
      "교수명": "",
      "수업시간/장소": "",
      "수업시간": "",
      "장소": ""
    },
    {
      "순번": "111",
      "강좌번호": "2487",
      "과목코드": "1002303",
      "과목명": "생활속의 화학",
      "학부(과)": "경영학과",
      "학년": "3",
      "이수구분": "",
      "영역구분": "",
      "학점": "2",
      "교수명": "",
      "수업시간/장소": "",
      "수업시간": "",
      "장소": ""
    },
    {
      "순번": "112",
      "강좌번호": "2481",
      "과목코드": "1002387",
      "과목명": "성격과 적응",
      "학부(과)": "경영학과",
      "학년": "3",
      "이수구분": "",
      "영역구분": "",
      "학점": "2",
      "교수명": "",
      "수업시간/장소": "",
      "수업시간": "",
      "장소": ""
    },
    {
      "순번": "113",
      "강좌번호": "2460",
      "과목코드": "1002428",
      "과목명": "성서예언과 종말",
      "학부(과)": "경영학과",
      "학년": "3",
      "이수구분": "",
      "영역구분": "인성교양",
      "학점": "2",
      "교수명": "",
      "수업시간/장소": "",
      "수업시간": "",
      "장소": ""
    },
    {
      "순번": "114",
      "강좌번호": "2459",
      "과목코드": "1002446",
      "과목명": "성소론",
      "학부(과)": "경영학과",
      "학년": "3",
      "이수구분": "",
      "영역구분": "인성교양",
      "학점": "2",
      "교수명": "",
      "수업시간/장소": "",
      "수업시간": "",
      "장소": ""
    },
    {
      "순번": "115",
      "강좌번호": "2482",
      "과목코드": "1002582",
      "과목명": "수학의 이해",
      "학부(과)": "경영학과",
      "학년": "3",
      "이수구분": "",
      "영역구분": "",
      "학점": "2",
      "교수명": "",
      "수업시간/장소": "",
      "수업시간": "",
      "장소": ""
    },
    {
      "순번": "116",
      "강좌번호": "2501",
      "과목코드": "1002668",
      "과목명": "시스템분석 및 설계",
      "학부(과)": "경영학과",
      "학년": "3",
      "이수구분": "",
      "영역구분": "",
      "학점": "3",
      "교수명": "",
      "수업시간/장소": "",
      "수업시간": "",
      "장소": ""
    },
    {
      "순번": "117",
      "강좌번호": "2464",
      "과목코드": "1002797",
      "과목명": "신앙과 경영",
      "학부(과)": "경영학과",
      "학년": "3",
      "이수구분": "",
      "영역구분": "",
      "학점": "2",
      "교수명": "",
      "수업시간/장소": "",
      "수업시간": "",
      "장소": ""
    },
    {
      "순번": "118",
      "강좌번호": "2491",
      "과목코드": "1003658",
      "과목명": "운동과 건강",
      "학부(과)": "경영학과",
      "학년": "3",
      "이수구분": "",
      "영역구분": "",
      "학점": "2",
      "교수명": "",
      "수업시간/장소": "",
      "수업시간": "",
      "장소": ""
    },
    {
      "순번": "119",
      "강좌번호": "2474",
      "과목코드": "1003779",
      "과목명": "윈도우프로그래밍 I",
      "학부(과)": "경영학과",
      "학년": "3",
      "이수구분": "",
      "영역구분": "",
      "학점": "3",
      "교수명": "",
      "수업시간/장소": "",
      "수업시간": "",
      "장소": ""
    },
    {
      "순번": "120",
      "강좌번호": "2489",
      "과목코드": "1003915",
      "과목명": "음악감상법I",
      "학부(과)": "경영학과",
      "학년": "3",
      "이수구분": "",
      "영역구분": "",
      "학점": "2",
      "교수명": "",
      "수업시간/장소": "",
      "수업시간": "",
      "장소": ""
    },
    {
      "순번": "121",
      "강좌번호": "2508",
      "과목코드": "1004066",
      "과목명": "인적자원관리론",
      "학부(과)": "경영학과",
      "학년": "3",
      "이수구분": "",
      "영역구분": "",
      "학점": "3",
      "교수명": "",
      "수업시간/장소": "",
      "수업시간": "",
      "장소": ""
    },
    {
      "순번": "122",
      "강좌번호": "2485",
      "과목코드": "1004071",
      "과목명": "인체와 생리",
      "학부(과)": "경영학과",
      "학년": "3",
      "이수구분": "",
      "영역구분": "",
      "학점": "2",
      "교수명": "",
      "수업시간/장소": "",
      "수업시간": "",
      "장소": ""
    },
    {
      "순번": "123",
      "강좌번호": "2466",
      "과목코드": "1004080",
      "과목명": "인터넷과 선교",
      "학부(과)": "경영학과",
      "학년": "3",
      "이수구분": "",
      "영역구분": "",
      "학점": "2",
      "교수명": "",
      "수업시간/장소": "",
      "수업시간": "",
      "장소": ""
    },
    {
      "순번": "124",
      "강좌번호": "2495",
      "과목코드": "1004175",
      "과목명": "일본문화와 사회",
      "학부(과)": "경영학과",
      "학년": "3",
      "이수구분": "",
      "영역구분": "",
      "학점": "2",
      "교수명": "",
      "수업시간/장소": "",
      "수업시간": "",
      "장소": ""
    },
    {
      "순번": "125",
      "강좌번호": "2505",
      "과목코드": "1004587",
      "과목명": "조직행동론",
      "학부(과)": "경영학과",
      "학년": "3",
      "이수구분": "",
      "영역구분": "",
      "학점": "3",
      "교수명": "",
      "수업시간/장소": "",
      "수업시간": "",
      "장소": ""
    },
    {
      "순번": "126",
      "강좌번호": "2513",
      "과목코드": "1004591",
      "과목명": "졸업논문",
      "학부(과)": "경영학과",
      "학년": "3",
      "이수구분": "",
      "영역구분": "",
      "학점": "2",
      "교수명": "",
      "수업시간/장소": "",
      "수업시간": "",
      "장소": ""
    },
    {
      "순번": "127",
      "강좌번호": "2509",
      "과목코드": "1004763",
      "과목명": "중급회계",
      "학부(과)": "경영학과",
      "학년": "3",
      "이수구분": "",
      "영역구분": "",
      "학점": "3",
      "교수명": "",
      "수업시간/장소": "",
      "수업시간": "",
      "장소": ""
    },
    {
      "순번": "128",
      "강좌번호": "2504",
      "과목코드": "1004794",
      "과목명": "증권시장론",
      "학부(과)": "경영학과",
      "학년": "3",
      "이수구분": "",
      "영역구분": "",
      "학점": "3",
      "교수명": "",
      "수업시간/장소": "",
      "수업시간": "",
      "장소": ""
    },
    {
      "순번": "129",
      "강좌번호": "2499",
      "과목코드": "1004872",
      "과목명": "창업실무",
      "학부(과)": "경영학과",
      "학년": "3",
      "이수구분": "",
      "영역구분": "",
      "학점": "2",
      "교수명": "",
      "수업시간/장소": "",
      "수업시간": "",
      "장소": ""
    },
    {
      "순번": "130",
      "강좌번호": "2469",
      "과목코드": "1004889",
      "과목명": "창조과학(구, 창조론과 과학)",
      "학부(과)": "경영학과",
      "학년": "3",
      "이수구분": "",
      "영역구분": "인성교양",
      "학점": "2",
      "교수명": "",
      "수업시간/장소": "",
      "수업시간": "",
      "장소": ""
    },
    {
      "순번": "131",
      "강좌번호": "2486",
      "과목코드": "1004914",
      "과목명": "천연치료법",
      "학부(과)": "경영학과",
      "학년": "3",
      "이수구분": "",
      "영역구분": "",
      "학점": "2",
      "교수명": "",
      "수업시간/장소": "",
      "수업시간": "",
      "장소": ""
    },
    {
      "순번": "132",
      "강좌번호": "2468",
      "과목코드": "1004933",
      "과목명": "청소년 이해와 상담",
      "학부(과)": "경영학과",
      "학년": "3",
      "이수구분": "",
      "영역구분": "",
      "학점": "2",
      "교수명": "",
      "수업시간/장소": "",
      "수업시간": "",
      "장소": ""
    },
    {
      "순번": "133",
      "강좌번호": "2467",
      "과목코드": "1004944",
      "과목명": "청소년지도법",
      "학부(과)": "경영학과",
      "학년": "3",
      "이수구분": "",
      "영역구분": "인성교양",
      "학점": "2",
      "교수명": "",
      "수업시간/장소": "",
      "수업시간": "",
      "장소": ""
    },
    {
      "순번": "134",
      "강좌번호": "2479",
      "과목코드": "1004995",
      "과목명": "중국어(초급)",
      "학부(과)": "경영학과",
      "학년": "3",
      "이수구분": "",
      "영역구분": "",
      "학점": "2",
      "교수명": "",
      "수업시간/장소": "",
      "수업시간": "",
      "장소": ""
    },
    {
      "순번": "135",
      "강좌번호": "2476",
      "과목코드": "1005090",
      "과목명": "컴퓨터 네트워크",
      "학부(과)": "경영학과",
      "학년": "3",
      "이수구분": "",
      "영역구분": "",
      "학점": "3",
      "교수명": "",
      "수업시간/장소": "",
      "수업시간": "",
      "장소": ""
    },
    {
      "순번": "136",
      "강좌번호": "2473",
      "과목코드": "1005095",
      "과목명": "컴퓨터 프로그래밍 I",
      "학부(과)": "경영학과",
      "학년": "3",
      "이수구분": "",
      "영역구분": "",
      "학점": "3",
      "교수명": "",
      "수업시간/장소": "",
      "수업시간": "",
      "장소": ""
    },
    {
      "순번": "137",
      "강좌번호": "2471",
      "과목코드": "1005099",
      "과목명": "컴퓨터 활용I",
      "학부(과)": "경영학과",
      "학년": "3",
      "이수구분": "",
      "영역구분": "컴퓨터활용",
      "학점": "2",
      "교수명": "",
      "수업시간/장소": "",
      "수업시간": "",
      "장소": ""
    },
    {
      "순번": "138",
      "강좌번호": "2472",
      "과목코드": "1005105",
      "과목명": "컴퓨터과학기초",
      "학부(과)": "경영학과",
      "학년": "3",
      "이수구분": "",
      "영역구분": "",
      "학점": "3",
      "교수명": "",
      "수업시간/장소": "",
      "수업시간": "",
      "장소": ""
    },
    {
      "순번": "139",
      "강좌번호": "2506",
      "과목코드": "1005395",
      "과목명": "한국경제론",
      "학부(과)": "경영학과",
      "학년": "3",
      "이수구분": "",
      "영역구분": "",
      "학점": "3",
      "교수명": "",
      "수업시간/장소": "",
      "수업시간": "",
      "장소": ""
    },
    {
      "순번": "140",
      "강좌번호": "2488",
      "과목코드": "1005487",
      "과목명": "합창 I",
      "학부(과)": "경영학과",
      "학년": "3",
      "이수구분": "",
      "영역구분": "",
      "학점": "2",
      "교수명": "",
      "수업시간/장소": "",
      "수업시간": "",
      "장소": ""
    },
    {
      "순번": "141",
      "강좌번호": "2502",
      "과목코드": "1005567",
      "과목명": "현대경영의 이해",
      "학부(과)": "경영학과",
      "학년": "3",
      "이수구분": "",
      "영역구분": "",
      "학점": "3",
      "교수명": "",
      "수업시간/장소": "",
      "수업시간": "",
      "장소": ""
    },
    {
      "순번": "142",
      "강좌번호": "2492",
      "과목코드": "1005585",
      "과목명": "현대사회와 광고",
      "학부(과)": "경영학과",
      "학년": "3",
      "이수구분": "",
      "영역구분": "",
      "학점": "2",
      "교수명": "",
      "수업시간/장소": "",
      "수업시간": "",
      "장소": ""
    },
    {
      "순번": "143",
      "강좌번호": "2496",
      "과목코드": "1005755",
      "과목명": "환경미학",
      "학부(과)": "경영학과",
      "학년": "3",
      "이수구분": "",
      "영역구분": "",
      "학점": "2",
      "교수명": "",
      "수업시간/장소": "",
      "수업시간": "",
      "장소": ""
    },
    {
      "순번": "144",
      "강좌번호": "2511",
      "과목코드": "1005783",
      "과목명": "회계감사론",
      "학부(과)": "경영학과",
      "학년": "3",
      "이수구분": "",
      "영역구분": "",
      "학점": "3",
      "교수명": "",
      "수업시간/장소": "",
      "수업시간": "",
      "장소": ""
    },
    {
      "순번": "145",
      "강좌번호": "2503",
      "과목코드": "1005784",
      "과목명": "회계원리",
      "학부(과)": "경영학과",
      "학년": "3",
      "이수구분": "",
      "영역구분": "",
      "학점": "3",
      "교수명": "",
      "수업시간/장소": "",
      "수업시간": "",
      "장소": ""
    },
    {
      "순번": "146",
      "강좌번호": "617",
      "과목코드": "1001003",
      "과목명": "국제경영학",
      "학부(과)": "경영학과",
      "학년": "4",
      "이수구분": "전공필수",
      "영역구분": "",
      "학점": "3",
      "교수명": "박철주",
      "수업시간/장소": "금2~4",
      "수업시간": "금2~4",
      "장소": ""
    },
    {
      "순번": "147",
      "강좌번호": "615",
      "과목코드": "1004066",
      "과목명": "인적자원관리론",
      "학부(과)": "경영학과",
      "학년": "4",
      "이수구분": "전공필수",
      "영역구분": "",
      "학점": "3",
      "교수명": "노중균",
      "수업시간/장소": "목1~3(사무엘관209호강의실)",
      "수업시간": "목1~3",
      "장소": "사무엘관209호강의실"
    },
    {
      "순번": "148",
      "강좌번호": "620",
      "과목코드": "1004591",
      "과목명": "졸업논문",
      "학부(과)": "경영학과",
      "학년": "4",
      "이수구분": "전공필수",
      "영역구분": "",
      "학점": "2",
      "교수명": "유한주",
      "수업시간/장소": "수5~6(사무엘관210호(PBL소형)강의실)",
      "수업시간": "수5~6",
      "장소": "사무엘관210호(PBL소형)강의실"
    },
    {
      "순번": "149",
      "강좌번호": "619",
      "과목코드": "1000640",
      "과목명": "경제학연습",
      "학부(과)": "경영학과",
      "학년": "4",
      "이수구분": "전공선택",
      "영역구분": "",
      "학점": "3",
      "교수명": "권혁용",
      "수업시간/장소": "월3(사무엘관209호강의실),수7~8(사무엘관209호강의실)",
      "수업시간": "월3,수7~8",
      "장소": "사무엘관209호강의실"
    },
    {
      "순번": "150",
      "강좌번호": "616",
      "과목코드": "1004763",
      "과목명": "중급회계",
      "학부(과)": "경영학과",
      "학년": "4",
      "이수구분": "전공선택",
      "영역구분": "",
      "학점": "3",
      "교수명": "최준환",
      "수업시간/장소": "화2~3(사무엘관210호(PBL소형)강의실),목4(사무엘관210호(PBL소형)강의실)",
      "수업시간": "화2~3,목4",
      "장소": "사무엘관210호(PBL소형)강의실"
    },
    {
      "순번": "151",
      "강좌번호": "618",
      "과목코드": "1005783",
      "과목명": "회계감사론",
      "학부(과)": "경영학과",
      "학년": "4",
      "이수구분": "전공선택",
      "영역구분": "",
      "학점": "3",
      "교수명": "송재현",
      "수업시간/장소": "월5~7",
      "수업시간": "월5~7",
      "장소": ""
    },
    {
      "순번": "152",
      "강좌번호": "614",
      "과목코드": "1000887",
      "과목명": "교육실습",
      "학부(과)": "경영학과",
      "학년": "4",
      "이수구분": "교직필수",
      "영역구분": "",
      "학점": "2",
      "교수명": "김봉진",
      "수업시간/장소": "월6~7",
      "수업시간": "월6~7",
      "장소": ""
    },
    {
      "순번": "153",
      "강좌번호": "2514",
      "과목코드": "1004903",
      "과목명": "채플",
      "학부(과)": "경영학과",
      "학년": "4",
      "이수구분": "채플",
      "영역구분": "",
      "학점": "0",
      "교수명": "",
      "수업시간/장소": "",
      "수업시간": "",
      "장소": ""
    },
    {
      "순번": "154",
      "강좌번호": "2519",
      "과목코드": "1000583",
      "과목명": "결혼과 가족관계",
      "학부(과)": "경영학과",
      "학년": "4",
      "이수구분": "",
      "영역구분": "인성교양",
      "학점": "2",
      "교수명": "",
      "수업시간/장소": "",
      "수업시간": "",
      "장소": ""
    },
    {
      "순번": "155",
      "강좌번호": "2565",
      "과목코드": "1000606",
      "과목명": "경영영어 II",
      "학부(과)": "경영학과",
      "학년": "4",
      "이수구분": "",
      "영역구분": "",
      "학점": "1",
      "교수명": "",
      "수업시간/장소": "",
      "수업시간": "",
      "장소": ""
    },
    {
      "순번": "156",
      "강좌번호": "2564",
      "과목코드": "1000620",
      "과목명": "경영통계론",
      "학부(과)": "경영학과",
      "학년": "4",
      "이수구분": "",
      "영역구분": "",
      "학점": "3",
      "교수명": "",
      "수업시간/장소": "",
      "수업시간": "",
      "장소": ""
    },
    {
      "순번": "157",
      "강좌번호": "2541",
      "과목코드": "1000757",
      "과목명": "공중보건",
      "학부(과)": "경영학과",
      "학년": "4",
      "이수구분": "",
      "영역구분": "",
      "학점": "2",
      "교수명": "",
      "수업시간/장소": "",
      "수업시간": "",
      "장소": ""
    },
    {
      "순번": "158",
      "강좌번호": "2527",
      "과목코드": "1000840",
      "과목명": "교내선교(Campus Ministry)",
      "학부(과)": "경영학과",
      "학년": "4",
      "이수구분": "",
      "영역구분": "",
      "학점": "2",
      "교수명": "",
      "수업시간/장소": "",
      "수업시간": "",
      "장소": ""
    },
    {
      "순번": "159",
      "강좌번호": "2530",
      "과목코드": "1000885",
      "과목명": "교육사회학",
      "학부(과)": "경영학과",
      "학년": "4",
      "이수구분": "",
      "영역구분": "",
      "학점": "2",
      "교수명": "",
      "수업시간/장소": "",
      "수업시간": "",
      "장소": ""
    },
    {
      "순번": "160",
      "강좌번호": "2529",
      "과목코드": "1000904",
      "과목명": "교육학개론",
      "학부(과)": "경영학과",
      "학년": "4",
      "이수구분": "",
      "영역구분": "",
      "학점": "2",
      "교수명": "",
      "수업시간/장소": "",
      "수업시간": "",
      "장소": ""
    },
    {
      "순번": "161",
      "강좌번호": "2521",
      "과목코드": "1000930",
      "과목명": "교회음악",
      "학부(과)": "경영학과",
      "학년": "4",
      "이수구분": "",
      "영역구분": "",
      "학점": "2",
      "교수명": "",
      "수업시간/장소": "",
      "수업시간": "",
      "장소": ""
    },
    {
      "순번": "162",
      "강좌번호": "2532",
      "과목코드": "1000995",
      "과목명": "국어 및 한문",
      "학부(과)": "경영학과",
      "학년": "4",
      "이수구분": "",
      "영역구분": "",
      "학점": "2",
      "교수명": "",
      "수업시간/장소": "",
      "수업시간": "",
      "장소": ""
    },
    {
      "순번": "163",
      "강좌번호": "2531",
      "과목코드": "1001109",
      "과목명": "기독교 사상(예수의 생애와 교훈)",
      "학부(과)": "경영학과",
      "학년": "4",
      "이수구분": "",
      "영역구분": "인성교양",
      "학점": "2",
      "교수명": "",
      "수업시간/장소": "",
      "수업시간": "",
      "장소": ""
    },
    {
      "순번": "164",
      "강좌번호": "2520",
      "과목코드": "1001124",
      "과목명": "기독교와 문화",
      "학부(과)": "경영학과",
      "학년": "4",
      "이수구분": "",
      "영역구분": "인성교양",
      "학점": "2",
      "교수명": "",
      "수업시간/장소": "",
      "수업시간": "",
      "장소": ""
    },
    {
      "순번": "165",
      "강좌번호": "2549",
      "과목코드": "1001619",
      "과목명": "매스컴의 이해",
      "학부(과)": "경영학과",
      "학년": "4",
      "이수구분": "",
      "영역구분": "",
      "학점": "2",
      "교수명": "",
      "수업시간/장소": "",
      "수업시간": "",
      "장소": ""
    },
    {
      "순번": "166",
      "강좌번호": "2567",
      "과목코드": "1002125",
      "과목명": "사회복지개론",
      "학부(과)": "경영학과",
      "학년": "4",
      "이수구분": "",
      "영역구분": "",
      "학점": "3",
      "교수명": "",
      "수업시간/장소": "",
      "수업시간": "",
      "장소": ""
    },
    {
      "순번": "167",
      "강좌번호": "2568",
      "과목코드": "1002137",
      "과목명": "사회복지실천론",
      "학부(과)": "경영학과",
      "학년": "4",
      "이수구분": "",
      "영역구분": "",
      "학점": "3",
      "교수명": "",
      "수업시간/장소": "",
      "수업시간": "",
      "장소": ""
    },
    {
      "순번": "168",
      "강좌번호": "2550",
      "과목코드": "1002162",
      "과목명": "사회봉사I",
      "학부(과)": "경영학과",
      "학년": "4",
      "이수구분": "",
      "영역구분": "",
      "학점": "2",
      "교수명": "",
      "수업시간/장소": "",
      "수업시간": "",
      "장소": ""
    },
    {
      "순번": "169",
      "강좌번호": "2537",
      "과목코드": "1002175",
      "과목명": "사회학",
      "학부(과)": "경영학과",
      "학년": "4",
      "이수구분": "",
      "영역구분": "",
      "학점": "2",
      "교수명": "",
      "수업시간/장소": "",
      "수업시간": "",
      "장소": ""
    },
    {
      "순번": "170",
      "강좌번호": "2561",
      "과목코드": "1002253",
      "과목명": "생산관리",
      "학부(과)": "경영학과",
      "학년": "4",
      "이수구분": "",
      "영역구분": "",
      "학점": "3",
      "교수명": "",
      "수업시간/장소": "",
      "수업시간": "",
      "장소": ""
    },
    {
      "순번": "171",
      "강좌번호": "2544",
      "과목코드": "1002286",
      "과목명": "생활과학",
      "학부(과)": "경영학과",
      "학년": "4",
      "이수구분": "",
      "영역구분": "",
      "학점": "2",
      "교수명": "",
      "수업시간/장소": "",
      "수업시간": "",
      "장소": ""
    },
    {
      "순번": "172",
      "강좌번호": "2533",
      "과목코드": "1002302",
      "과목명": "생활속의 한문",
      "학부(과)": "경영학과",
      "학년": "4",
      "이수구분": "",
      "영역구분": "",
      "학점": "2",
      "교수명": "",
      "수업시간/장소": "",
      "수업시간": "",
      "장소": ""
    },
    {
      "순번": "173",
      "강좌번호": "2545",
      "과목코드": "1002310",
      "과목명": "생활원예",
      "학부(과)": "경영학과",
      "학년": "4",
      "이수구분": "",
      "영역구분": "",
      "학점": "2",
      "교수명": "",
      "수업시간/장소": "",
      "수업시간": "",
      "장소": ""
    },
    {
      "순번": "174",
      "강좌번호": "2539",
      "과목코드": "1002387",
      "과목명": "성격과 적응",
      "학부(과)": "경영학과",
      "학년": "4",
      "이수구분": "",
      "영역구분": "",
      "학점": "2",
      "교수명": "",
      "수업시간/장소": "",
      "수업시간": "",
      "장소": ""
    },
    {
      "순번": "175",
      "강좌번호": "2516",
      "과목코드": "1002428",
      "과목명": "성서예언과 종말",
      "학부(과)": "경영학과",
      "학년": "4",
      "이수구분": "",
      "영역구분": "인성교양",
      "학점": "2",
      "교수명": "",
      "수업시간/장소": "",
      "수업시간": "",
      "장소": ""
    },
    {
      "순번": "176",
      "강좌번호": "2515",
      "과목코드": "1002446",
      "과목명": "성소론",
      "학부(과)": "경영학과",
      "학년": "4",
      "이수구분": "",
      "영역구분": "인성교양",
      "학점": "2",
      "교수명": "",
      "수업시간/장소": "",
      "수업시간": "",
      "장소": ""
    },
    {
      "순번": "177",
      "강좌번호": "2562",
      "과목코드": "1002538",
      "과목명": "소비자행동론",
      "학부(과)": "경영학과",
      "학년": "4",
      "이수구분": "",
      "영역구분": "",
      "학점": "3",
      "교수명": "",
      "수업시간/장소": "",
      "수업시간": "",
      "장소": ""
    },
    {
      "순번": "178",
      "강좌번호": "2518",
      "과목코드": "1002797",
      "과목명": "신앙과 경영",
      "학부(과)": "경영학과",
      "학년": "4",
      "이수구분": "",
      "영역구분": "",
      "학점": "2",
      "교수명": "",
      "수업시간/장소": "",
      "수업시간": "",
      "장소": ""
    },
    {
      "순번": "179",
      "강좌번호": "2551",
      "과목코드": "1003188",
      "과목명": "여성학",
      "학부(과)": "경영학과",
      "학년": "4",
      "이수구분": "",
      "영역구분": "",
      "학점": "2",
      "교수명": "",
      "수업시간/장소": "",
      "수업시간": "",
      "장소": ""
    },
    {
      "순번": "180",
      "강좌번호": "2553",
      "과목코드": "1003192",
      "과목명": "역사 유적의 탐방",
      "학부(과)": "경영학과",
      "학년": "4",
      "이수구분": "",
      "영역구분": "",
      "학점": "2",
      "교수명": "",
      "수업시간/장소": "",
      "수업시간": "",
      "장소": ""
    },
    {
      "순번": "181",
      "강좌번호": "2534",
      "과목코드": "1003252",
      "과목명": "영문법(초급)",
      "학부(과)": "경영학과",
      "학년": "4",
      "이수구분": "",
      "영역구분": "",
      "학점": "2",
      "교수명": "",
      "수업시간/장소": "",
      "수업시간": "",
      "장소": ""
    },
    {
      "순번": "182",
      "강좌번호": "2542",
      "과목코드": "1003335",
      "과목명": "영양과 건강관리",
      "학부(과)": "경영학과",
      "학년": "4",
      "이수구분": "",
      "영역구분": "",
      "학점": "2",
      "교수명": "",
      "수업시간/장소": "",
      "수업시간": "",
      "장소": ""
    },
    {
      "순번": "183",
      "강좌번호": "2547",
      "과목코드": "1003658",
      "과목명": "운동과 건강",
      "학부(과)": "경영학과",
      "학년": "4",
      "이수구분": "",
      "영역구분": "",
      "학점": "2",
      "교수명": "",
      "수업시간/장소": "",
      "수업시간": "",
      "장소": ""
    },
    {
      "순번": "184",
      "강좌번호": "2543",
      "과목코드": "1003939",
      "과목명": "음악치료",
      "학부(과)": "경영학과",
      "학년": "4",
      "이수구분": "",
      "영역구분": "",
      "학점": "2",
      "교수명": "",
      "수업시간/장소": "",
      "수업시간": "",
      "장소": ""
    },
    {
      "순번": "185",
      "강좌번호": "2566",
      "과목코드": "1003995",
      "과목명": "의사결정론",
      "학부(과)": "경영학과",
      "학년": "4",
      "이수구분": "",
      "영역구분": "",
      "학점": "3",
      "교수명": "",
      "수업시간/장소": "",
      "수업시간": "",
      "장소": ""
    },
    {
      "순번": "186",
      "강좌번호": "2540",
      "과목코드": "1004033",
      "과목명": "인간관계론",
      "학부(과)": "경영학과",
      "학년": "4",
      "이수구분": "",
      "영역구분": "",
      "학점": "2",
      "교수명": "",
      "수업시간/장소": "",
      "수업시간": "",
      "장소": ""
    },
    {
      "순번": "187",
      "강좌번호": "2523",
      "과목코드": "1004080",
      "과목명": "인터넷과 선교",
      "학부(과)": "경영학과",
      "학년": "4",
      "이수구분": "",
      "영역구분": "",
      "학점": "2",
      "교수명": "",
      "수업시간/장소": "",
      "수업시간": "",
      "장소": ""
    },
    {
      "순번": "188",
      "강좌번호": "2538",
      "과목코드": "1004143",
      "과목명": "일반심리학",
      "학부(과)": "경영학과",
      "학년": "4",
      "이수구분": "",
      "영역구분": "",
      "학점": "2",
      "교수명": "",
      "수업시간/장소": "",
      "수업시간": "",
      "장소": ""
    },
    {
      "순번": "189",
      "강좌번호": "2552",
      "과목코드": "1004175",
      "과목명": "일본문화와 사회",
      "학부(과)": "경영학과",
      "학년": "4",
      "이수구분": "",
      "영역구분": "",
      "학점": "2",
      "교수명": "",
      "수업시간/장소": "",
      "수업시간": "",
      "장소": ""
    },
    {
      "순번": "190",
      "강좌번호": "2563",
      "과목코드": "1004355",
      "과목명": "재무관리",
      "학부(과)": "경영학과",
      "학년": "4",
      "이수구분": "",
      "영역구분": "",
      "학점": "3",
      "교수명": "",
      "수업시간/장소": "",
      "수업시간": "",
      "장소": ""
    },
    {
      "순번": "191",
      "강좌번호": "2522",
      "과목코드": "1004414",
      "과목명": "전도법",
      "학부(과)": "경영학과",
      "학년": "4",
      "이수구분": "",
      "영역구분": "",
      "학점": "2",
      "교수명": "",
      "수업시간/장소": "",
      "수업시간": "",
      "장소": ""
    },
    {
      "순번": "192",
      "강좌번호": "2546",
      "과목코드": "1004458",
      "과목명": "전통음악의 이해",
      "학부(과)": "경영학과",
      "학년": "4",
      "이수구분": "",
      "영역구분": "",
      "학점": "2",
      "교수명": "",
      "수업시간/장소": "",
      "수업시간": "",
      "장소": ""
    },
    {
      "순번": "193",
      "강좌번호": "2559",
      "과목코드": "1004587",
      "과목명": "조직행동론",
      "학부(과)": "경영학과",
      "학년": "4",
      "이수구분": "",
      "영역구분": "",
      "학점": "3",
      "교수명": "",
      "수업시간/장소": "",
      "수업시간": "",
      "장소": ""
    },
    {
      "순번": "194",
      "강좌번호": "2558",
      "과목코드": "1004794",
      "과목명": "증권시장론",
      "학부(과)": "경영학과",
      "학년": "4",
      "이수구분": "",
      "영역구분": "",
      "학점": "3",
      "교수명": "",
      "수업시간/장소": "",
      "수업시간": "",
      "장소": ""
    },
    {
      "순번": "195",
      "강좌번호": "2555",
      "과목코드": "1004872",
      "과목명": "창업실무",
      "학부(과)": "경영학과",
      "학년": "4",
      "이수구분": "",
      "영역구분": "",
      "학점": "2",
      "교수명": "",
      "수업시간/장소": "",
      "수업시간": "",
      "장소": ""
    },
    {
      "순번": "196",
      "강좌번호": "2526",
      "과목코드": "1004889",
      "과목명": "창조과학(구, 창조론과 과학)",
      "학부(과)": "경영학과",
      "학년": "4",
      "이수구분": "",
      "영역구분": "인성교양",
      "학점": "2",
      "교수명": "",
      "수업시간/장소": "",
      "수업시간": "",
      "장소": ""
    },
    {
      "순번": "197",
      "강좌번호": "2525",
      "과목코드": "1004933",
      "과목명": "청소년 이해와 상담",
      "학부(과)": "경영학과",
      "학년": "4",
      "이수구분": "",
      "영역구분": "",
      "학점": "2",
      "교수명": "",
      "수업시간/장소": "",
      "수업시간": "",
      "장소": ""
    },
    {
      "순번": "198",
      "강좌번호": "2524",
      "과목코드": "1004944",
      "과목명": "청소년지도법",
      "학부(과)": "경영학과",
      "학년": "4",
      "이수구분": "",
      "영역구분": "인성교양",
      "학점": "2",
      "교수명": "",
      "수업시간/장소": "",
      "수업시간": "",
      "장소": ""
    },
    {
      "순번": "199",
      "강좌번호": "2535",
      "과목코드": "1005013",
      "과목명": "초급영어어휘",
      "학부(과)": "경영학과",
      "학년": "4",
      "이수구분": "",
      "영역구분": "",
      "학점": "2",
      "교수명": "",
      "수업시간/장소": "",
      "수업시간": "",
      "장소": ""
    },
    {
      "순번": "200",
      "강좌번호": "2528",
      "과목코드": "1005099",
      "과목명": "컴퓨터 활용I",
      "학부(과)": "경영학과",
      "학년": "4",
      "이수구분": "",
      "영역구분": "컴퓨터활용",
      "학점": "2",
      "교수명": "",
      "수업시간/장소": "",
      "수업시간": "",
      "장소": ""
    },
    {
      "순번": "201",
      "강좌번호": "2517",
      "과목코드": "1005171",
      "과목명": "크리스챤 리더쉽",
      "학부(과)": "경영학과",
      "학년": "4",
      "이수구분": "",
      "영역구분": "인성교양",
      "학점": "2",
      "교수명": "",
      "수업시간/장소": "",
      "수업시간": "",
      "장소": ""
    },
    {
      "순번": "202",
      "강좌번호": "2569",
      "과목코드": "1005206",
      "과목명": "통계자료 분석",
      "학부(과)": "경영학과",
      "학년": "4",
      "이수구분": "",
      "영역구분": "",
      "학점": "3",
      "교수명": "",
      "수업시간/장소": "",
      "수업시간": "",
      "장소": ""
    },
    {
      "순번": "203",
      "강좌번호": "2560",
      "과목코드": "1005395",
      "과목명": "한국경제론",
      "학부(과)": "경영학과",
      "학년": "4",
      "이수구분": "",
      "영역구분": "",
      "학점": "3",
      "교수명": "",
      "수업시간/장소": "",
      "수업시간": "",
      "장소": ""
    },
    {
      "순번": "204",
      "강좌번호": "2556",
      "과목코드": "1005567",
      "과목명": "현대경영의 이해",
      "학부(과)": "경영학과",
      "학년": "4",
      "이수구분": "",
      "영역구분": "",
      "학점": "3",
      "교수명": "",
      "수업시간/장소": "",
      "수업시간": "",
      "장소": ""
    },
    {
      "순번": "205",
      "강좌번호": "2548",
      "과목코드": "1005585",
      "과목명": "현대사회와 광고",
      "학부(과)": "경영학과",
      "학년": "4",
      "이수구분": "",
      "영역구분": "",
      "학점": "2",
      "교수명": "",
      "수업시간/장소": "",
      "수업시간": "",
      "장소": ""
    },
    {
      "순번": "206",
      "강좌번호": "2536",
      "과목코드": "1005638",
      "과목명": "현실경제의 이해",
      "학부(과)": "경영학과",
      "학년": "4",
      "이수구분": "",
      "영역구분": "",
      "학점": "2",
      "교수명": "",
      "수업시간/장소": "",
      "수업시간": "",
      "장소": ""
    },
    {
      "순번": "207",
      "강좌번호": "2554",
      "과목코드": "1005755",
      "과목명": "환경미학",
      "학부(과)": "경영학과",
      "학년": "4",
      "이수구분": "",
      "영역구분": "",
      "학점": "2",
      "교수명": "",
      "수업시간/장소": "",
      "수업시간": "",
      "장소": ""
    },
    {
      "순번": "208",
      "강좌번호": "2557",
      "과목코드": "1005784",
      "과목명": "회계원리",
      "학부(과)": "경영학과",
      "학년": "4",
      "이수구분": "",
      "영역구분": "",
      "학점": "3",
      "교수명": "",
      "수업시간/장소": "",
      "수업시간": "",
      "장소": ""
    }
  ]
}