{
  "api": [
    {
      "순번": "1",
      "강좌번호": "1685",
      "과목코드": "1001058",
      "과목명": "글로벌리더십교육Ⅰ",
      "학부(과)": "중국어학과",
      "학년": "1",
      "이수구분": "교양필수",
      "영역구분": "일반선택영역",
      "학점": "1",
      "교수명": "비젼드림센터3399-3076",
      "수업시간/장소": "",
      "수업시간": "",
      "장소": ""
    },
    {
      "순번": "2",
      "강좌번호": "97",
      "과목코드": "1001135",
      "과목명": "종교와인생(구,기독교입문)",
      "학부(과)": "중국어학과",
      "학년": "1",
      "이수구분": "교양필수",
      "영역구분": "인성교양",
      "학점": "2",
      "교수명": "박희문",
      "수업시간/장소": "수5~6",
      "수업시간": "수5~6",
      "장소": ""
    },
    {
      "순번": "3",
      "강좌번호": "98",
      "과목코드": "1005796",
      "과목명": "흡연 음주예방 교육",
      "학부(과)": "중국어학과",
      "학년": "1",
      "이수구분": "교양필수",
      "영역구분": "",
      "학점": "0",
      "교수명": "금연금주클리닉",
      "수업시간/장소": "목5(대강당(메인))",
      "수업시간": "목5",
      "장소": "대강당(메인)"
    },
    {
      "순번": "4",
      "강좌번호": "2237",
      "과목코드": "1000693",
      "과목명": "고급중국어",
      "학부(과)": "중국어학과",
      "학년": "1",
      "이수구분": "전공선택",
      "영역구분": "",
      "학점": "4",
      "교수명": "교류대학",
      "수업시간/장소": "",
      "수업시간": "",
      "장소": ""
    },
    {
      "순번": "5",
      "강좌번호": "2236",
      "과목코드": "1001785",
      "과목명": "미디어중국어",
      "학부(과)": "중국어학과",
      "학년": "1",
      "이수구분": "전공선택",
      "영역구분": "",
      "학점": "1",
      "교수명": "교류대학",
      "수업시간/장소": "",
      "수업시간": "",
      "장소": ""
    },
    {
      "순번": "6",
      "강좌번호": "2238",
      "과목코드": "1002066",
      "과목명": "비즈니스중국어",
      "학부(과)": "중국어학과",
      "학년": "1",
      "이수구분": "전공선택",
      "영역구분": "",
      "학점": "4",
      "교수명": "교류대학",
      "수업시간/장소": "",
      "수업시간": "",
      "장소": ""
    },
    {
      "순번": "7",
      "강좌번호": "2207",
      "과목코드": "1002660",
      "과목명": "시사중국어",
      "학부(과)": "중국어학과",
      "학년": "1",
      "이수구분": "전공선택",
      "영역구분": "",
      "학점": "4",
      "교수명": "교류대학",
      "수업시간/장소": "",
      "수업시간": "",
      "장소": ""
    },
    {
      "순번": "8",
      "강좌번호": "2235",
      "과목코드": "1004650",
      "과목명": "중국문학사",
      "학부(과)": "중국어학과",
      "학년": "1",
      "이수구분": "전공선택",
      "영역구분": "",
      "학점": "4",
      "교수명": "교류대학",
      "수업시간/장소": "",
      "수업시간": "",
      "장소": ""
    },
    {
      "순번": "9",
      "강좌번호": "92",
      "과목코드": "1004660",
      "과목명": "중국사회와 문화",
      "학부(과)": "중국어학과",
      "학년": "1",
      "이수구분": "전공선택",
      "영역구분": "",
      "학점": "3",
      "교수명": "백지연",
      "수업시간/장소": "화3~5(바울관303호(AIC프로젝트 LAB실))",
      "수업시간": "화3~5",
      "장소": "바울관303호(AIC프로젝트 LAB실)"
    },
    {
      "순번": "10",
      "강좌번호": "2206",
      "과목코드": "1004670",
      "과목명": "중국어 작문",
      "학부(과)": "중국어학과",
      "학년": "1",
      "이수구분": "전공선택",
      "영역구분": "",
      "학점": "4",
      "교수명": "교류대학",
      "수업시간/장소": "",
      "수업시간": "",
      "장소": ""
    },
    {
      "순번": "11",
      "강좌번호": "2208",
      "과목코드": "1004671",
      "과목명": "중국어 토론",
      "학부(과)": "중국어학과",
      "학년": "1",
      "이수구분": "전공선택",
      "영역구분": "",
      "학점": "4",
      "교수명": "교류대학",
      "수업시간/장소": "",
      "수업시간": "",
      "장소": ""
    },
    {
      "순번": "12",
      "강좌번호": "93",
      "과목코드": "1005039",
      "과목명": "초급중국어 I",
      "학부(과)": "중국어학과",
      "학년": "1",
      "이수구분": "전공선택",
      "영역구분": "",
      "학점": "3",
      "교수명": "함현자",
      "수업시간/장소": "화2(바울관303호(AIC프로젝트 LAB실)),수2~3(바울관402호강의실)",
      "수업시간": "화2,수2~3",
      "장소": "바울관303호(AIC프로젝트 LAB실),바울관402호강의실"
    },
    {
      "순번": "13",
      "강좌번호": "94",
      "과목코드": "1005046",
      "과목명": "초급중국어회화I",
      "학부(과)": "중국어학과",
      "학년": "1",
      "이수구분": "전공선택",
      "영역구분": "",
      "학점": "3",
      "교수명": "김낙철",
      "수업시간/장소": "월3(바울관402호강의실),목2~3(바울관303호(AIC프로젝트 LAB실))",
      "수업시간": "월3,목2~3",
      "장소": "바울관303호(AIC프로젝트 LAB실),바울관402호강의실"
    },
    {
      "순번": "14",
      "강좌번호": "95",
      "과목코드": "1005046",
      "과목명": "초급중국어회화I",
      "학부(과)": "중국어학과",
      "학년": "1",
      "이수구분": "전공선택",
      "영역구분": "",
      "학점": "3",
      "교수명": "박민수",
      "수업시간/장소": "월3,목2~3",
      "수업시간": "월3,목2~3",
      "장소": ""
    },
    {
      "순번": "15",
      "강좌번호": "2205",
      "과목코드": "1005215",
      "과목명": "통역중국어",
      "학부(과)": "중국어학과",
      "학년": "1",
      "이수구분": "전공선택",
      "영역구분": "",
      "학점": "4",
      "교수명": "교류대학",
      "수업시간/장소": "",
      "수업시간": "",
      "장소": ""
    },
    {
      "순번": "16",
      "강좌번호": "96",
      "과목코드": "1004903",
      "과목명": "채플",
      "학부(과)": "중국어학과",
      "학년": "1",
      "이수구분": "채플",
      "영역구분": "",
      "학점": "0",
      "교수명": "교목처",
      "수업시간/장소": "월2(대강당(메인))",
      "수업시간": "월2",
      "장소": "대강당(메인)"
    },
    {
      "순번": "17",
      "강좌번호": "2056",
      "과목코드": "1001119",
      "과목명": "생활과 윤리",
      "학부(과)": "중국어학과",
      "학년": "2",
      "이수구분": "교양필수",
      "영역구분": "인성교양",
      "학점": "2",
      "교수명": "박희문",
      "수업시간/장소": "월5~6(바울관202호(PBL)강의실)",
      "수업시간": "월5~6",
      "장소": "바울관202호(PBL)강의실"
    },
    {
      "순번": "18",
      "강좌번호": "99",
      "과목코드": "1004650",
      "과목명": "중국문학사",
      "학부(과)": "중국어학과",
      "학년": "2",
      "이수구분": "전공선택",
      "영역구분": "",
      "학점": "3",
      "교수명": "김낙철",
      "수업시간/장소": "월2(바울관402호강의실),수5~6(바울관303호(AIC프로젝트 LAB실))",
      "수업시간": "월2,수5~6",
      "장소": "바울관303호(AIC프로젝트 LAB실),바울관402호강의실"
    },
    {
      "순번": "19",
      "강좌번호": "103",
      "과목코드": "1004687",
      "과목명": "중국어연습 I",
      "학부(과)": "중국어학과",
      "학년": "2",
      "이수구분": "전공선택",
      "영역구분": "",
      "학점": "3",
      "교수명": "박민수",
      "수업시간/장소": "월4,수2~3",
      "수업시간": "월4,수2~3",
      "장소": ""
    },
    {
      "순번": "20",
      "강좌번호": "100",
      "과목코드": "1004747",
      "과목명": "중급중국어 I",
      "학부(과)": "중국어학과",
      "학년": "2",
      "이수구분": "전공선택",
      "영역구분": "",
      "학점": "3",
      "교수명": "함현자",
      "수업시간/장소": "화4~5(바울관403호강의실),목5(바울관403호강의실)",
      "수업시간": "화4~5,목5",
      "장소": "바울관403호강의실"
    },
    {
      "순번": "21",
      "강좌번호": "102",
      "과목코드": "1004757",
      "과목명": "중급중국어회화 I",
      "학부(과)": "중국어학과",
      "학년": "2",
      "이수구분": "전공선택",
      "영역구분": "",
      "학점": "3",
      "교수명": "진현",
      "수업시간/장소": "화3,목1~2(바울관306호강의실)",
      "수업시간": "화3,목1~2",
      "장소": "바울관306호강의실"
    },
    {
      "순번": "22",
      "강좌번호": "104",
      "과목코드": "1004903",
      "과목명": "채플",
      "학부(과)": "중국어학과",
      "학년": "2",
      "이수구분": "채플",
      "영역구분": "",
      "학점": "0",
      "교수명": "교목처",
      "수업시간/장소": "월3(대강당(메인))",
      "수업시간": "월3",
      "장소": "대강당(메인)"
    },
    {
      "순번": "23",
      "강좌번호": "111",
      "과목코드": "1000184",
      "과목명": "HSK특강I",
      "학부(과)": "중국어학과",
      "학년": "3",
      "이수구분": "전공선택",
      "영역구분": "",
      "학점": "3",
      "교수명": "백지연",
      "수업시간/장소": "화6~8(바울관401호식음료실습실)",
      "수업시간": "화6~8",
      "장소": "바울관401호식음료실습실"
    },
    {
      "순번": "24",
      "강좌번호": "108",
      "과목코드": "1000696",
      "과목명": "고급중국어I",
      "학부(과)": "중국어학과",
      "학년": "3",
      "이수구분": "전공선택",
      "영역구분": "",
      "학점": "3",
      "교수명": "함현자",
      "수업시간/장소": "월1~2(바울관403호강의실),수1(바울관403호강의실)",
      "수업시간": "월1~2,수1",
      "장소": "바울관403호강의실"
    },
    {
      "순번": "25",
      "강좌번호": "109",
      "과목코드": "1000701",
      "과목명": "고급중국어회화 I",
      "학부(과)": "중국어학과",
      "학년": "3",
      "이수구분": "전공선택",
      "영역구분": "",
      "학점": "3",
      "교수명": "갈장강",
      "수업시간/장소": "목1~3(바울관403호강의실)",
      "수업시간": "목1~3",
      "장소": "바울관403호강의실"
    },
    {
      "순번": "26",
      "강좌번호": "107",
      "과목코드": "1004670",
      "과목명": "중국어 작문",
      "학부(과)": "중국어학과",
      "학년": "3",
      "이수구분": "전공선택",
      "영역구분": "",
      "학점": "3",
      "교수명": "박민수",
      "수업시간/장소": "수4~6(바울관402호강의실)",
      "수업시간": "수4~6",
      "장소": "바울관402호강의실"
    },
    {
      "순번": "27",
      "강좌번호": "112",
      "과목코드": "1004685",
      "과목명": "중국어스피치",
      "학부(과)": "중국어학과",
      "학년": "3",
      "이수구분": "전공선택",
      "영역구분": "",
      "학점": "3",
      "교수명": "김보경",
      "수업시간/장소": "목5~7(바울관402호강의실)",
      "수업시간": "목5~7",
      "장소": "바울관402호강의실"
    },
    {
      "순번": "28",
      "강좌번호": "110",
      "과목코드": "1005216",
      "과목명": "통역중국어 I",
      "학부(과)": "중국어학과",
      "학년": "3",
      "이수구분": "전공선택",
      "영역구분": "",
      "학점": "3",
      "교수명": "김보경",
      "수업시간/장소": "월4~6(바울관403호강의실)",
      "수업시간": "월4~6",
      "장소": "바울관403호강의실"
    },
    {
      "순번": "29",
      "강좌번호": "872",
      "과목코드": "1005421",
      "과목명": "한국어교육 방법론",
      "학부(과)": "중국어학과",
      "학년": "3",
      "이수구분": "전공선택",
      "영역구분": "",
      "학점": "3",
      "교수명": "Zhenxuan Li",
      "수업시간/장소": "금2~4",
      "수업시간": "금2~4",
      "장소": ""
    },
    {
      "순번": "30",
      "강좌번호": "106",
      "과목코드": "1005629",
      "과목명": "현대 중국사회의 이해",
      "학부(과)": "중국어학과",
      "학년": "3",
      "이수구분": "전공선택",
      "영역구분": "",
      "학점": "3",
      "교수명": "박언진",
      "수업시간/장소": "화1~3(바울관402호강의실)",
      "수업시간": "화1~3",
      "장소": "바울관402호강의실"
    },
    {
      "순번": "31",
      "강좌번호": "113",
      "과목코드": "1004664",
      "과목명": "중국어 교과교육론",
      "학부(과)": "중국어학과",
      "학년": "3",
      "이수구분": "교직필수",
      "영역구분": "",
      "학점": "3",
      "교수명": "김보경",
      "수업시간/장소": "월10(신학관105호강의실(소형수업행동분석실II)),월8~9",
      "수업시간": "월10,월8~9",
      "장소": "신학관105호강의실(소형수업행동분석실II)"
    },
    {
      "순번": "32",
      "강좌번호": "114",
      "과목코드": "1004903",
      "과목명": "채플",
      "학부(과)": "중국어학과",
      "학년": "3",
      "이수구분": "채플",
      "영역구분": "",
      "학점": "0",
      "교수명": "교목처",
      "수업시간/장소": "수2(대강당(메인))",
      "수업시간": "수2",
      "장소": "대강당(메인)"
    },
    {
      "순번": "33",
      "강좌번호": "841",
      "과목코드": "1004377",
      "과목명": "전공논문 연구 및 작성",
      "학부(과)": "중국어학과",
      "학년": "4",
      "이수구분": "전공필수",
      "영역구분": "",
      "학점": "0",
      "교수명": "김낙철",
      "수업시간/장소": "월0,수0",
      "수업시간": "월0,수0",
      "장소": ""
    },
    {
      "순번": "34",
      "강좌번호": "843",
      "과목코드": "1000791",
      "과목명": "관광중국어회화",
      "학부(과)": "중국어학과",
      "학년": "4",
      "이수구분": "전공선택",
      "영역구분": "",
      "학점": "3",
      "교수명": "김낙철",
      "수업시간/장소": "월5~7",
      "수업시간": "월5~7",
      "장소": ""
    },
    {
      "순번": "35",
      "강좌번호": "116",
      "과목코드": "1002072",
      "과목명": "비지니스 중국어I",
      "학부(과)": "중국어학과",
      "학년": "4",
      "이수구분": "전공선택",
      "영역구분": "",
      "학점": "3",
      "교수명": "박언진",
      "수업시간/장소": "화5~7",
      "수업시간": "화5~7",
      "장소": ""
    },
    {
      "순번": "36",
      "강좌번호": "115",
      "과목코드": "1002660",
      "과목명": "시사중국어",
      "학부(과)": "중국어학과",
      "학년": "4",
      "이수구분": "전공선택",
      "영역구분": "",
      "학점": "3",
      "교수명": "함현자",
      "수업시간/장소": "월3(바울관403호강의실),수5~6",
      "수업시간": "월3,수5~6",
      "장소": "바울관403호강의실"
    },
    {
      "순번": "37",
      "강좌번호": "842",
      "과목코드": "1004681",
      "과목명": "중국어면접특강",
      "학부(과)": "중국어학과",
      "학년": "4",
      "이수구분": "전공선택",
      "영역구분": "",
      "학점": "3",
      "교수명": "박민수",
      "수업시간/장소": "화1~3(바울관312호강의실)",
      "수업시간": "화1~3",
      "장소": "바울관312호강의실"
    },
    {
      "순번": "38",
      "강좌번호": "117",
      "과목코드": "1004903",
      "과목명": "채플",
      "학부(과)": "중국어학과",
      "학년": "4",
      "이수구분": "채플",
      "영역구분": "",
      "학점": "0",
      "교수명": "교목처",
      "수업시간/장소": "수3(대강당(메인))",
      "수업시간": "수3",
      "장소": "대강당(메인)"
    }
  ]
}