{
  "api": [
    {
      "순번": "1",
      "강좌번호": "525",
      "과목코드": "1001117",
      "과목명": "인성과사회",
      "학부(과)": "사회복지학과",
      "학년": "1",
      "이수구분": "교양필수",
      "영역구분": "",
      "학점": "2",
      "교수명": "오성규",
      "수업시간/장소": "월1~2(사무엘관109호강의실)",
      "수업시간": "월1~2",
      "장소": "사무엘관109호강의실"
    },
    {
      "순번": "2",
      "강좌번호": "534",
      "과목코드": "1005996",
      "과목명": "인생설계와 진로 I",
      "학부(과)": "사회복지학과",
      "학년": "1",
      "이수구분": "교양필수",
      "영역구분": "",
      "학점": "1",
      "교수명": "정종화",
      "수업시간/장소": "화9(사무엘관107호강의실)",
      "수업시간": "화9",
      "장소": "사무엘관107호강의실"
    },
    {
      "순번": "3",
      "강좌번호": "533",
      "과목코드": "1005996",
      "과목명": "인생설계와 진로 I",
      "학부(과)": "사회복지학과",
      "학년": "1",
      "이수구분": "교양필수",
      "영역구분": "",
      "학점": "1",
      "교수명": "윤재영",
      "수업시간/장소": "화9(사무엘관109호강의실)",
      "수업시간": "화9",
      "장소": "사무엘관109호강의실"
    },
    {
      "순번": "4",
      "강좌번호": "524",
      "과목코드": "1005996",
      "과목명": "인생설계와 진로 I",
      "학부(과)": "사회복지학과",
      "학년": "1",
      "이수구분": "교양필수",
      "영역구분": "",
      "학점": "1",
      "교수명": "조미숙",
      "수업시간/장소": "화9(사무엘관108호(PBL소형)강의실)",
      "수업시간": "화9",
      "장소": "사무엘관108호(PBL소형)강의실"
    },
    {
      "순번": "5",
      "강좌번호": "522",
      "과목코드": "1002125",
      "과목명": "사회복지학개론",
      "학부(과)": "사회복지학과",
      "학년": "1",
      "이수구분": "전공필수",
      "영역구분": "",
      "학점": "3",
      "교수명": "윤재영",
      "수업시간/장소": "월6~8(사무엘관107호강의실)",
      "수업시간": "월6~8",
      "장소": "사무엘관107호강의실"
    },
    {
      "순번": "6",
      "강좌번호": "521",
      "과목코드": "1002128",
      "과목명": "사회복지역사",
      "학부(과)": "사회복지학과",
      "학년": "1",
      "이수구분": "전공선택",
      "영역구분": "",
      "학점": "3",
      "교수명": "조재형",
      "수업시간/장소": "수4~6(사무엘관109호강의실)",
      "수업시간": "수4~6",
      "장소": "사무엘관109호강의실"
    },
    {
      "순번": "7",
      "강좌번호": "520",
      "과목코드": "1002157",
      "과목명": "사회복지현장의 이해",
      "학부(과)": "사회복지학과",
      "학년": "1",
      "이수구분": "전공선택",
      "영역구분": "",
      "학점": "3",
      "교수명": "장순욱",
      "수업시간/장소": "금2~4(사무엘관108호(PBL소형)강의실)",
      "수업시간": "금2~4",
      "장소": "사무엘관108호(PBL소형)강의실"
    },
    {
      "순번": "8",
      "강좌번호": "520",
      "과목코드": "1002157",
      "과목명": "사회복지현장의 이해",
      "학부(과)": "사회복지학과",
      "학년": "1",
      "이수구분": "전공선택",
      "영역구분": "",
      "학점": "3",
      "교수명": "장순욱",
      "수업시간/장소": "금2~4(사무엘관108호(PBL소형)강의실)",
      "수업시간": "금2~4",
      "장소": "사무엘관108호(PBL소형)강의실"
    },
    {
      "순번": "9",
      "강좌번호": "1393",
      "과목코드": "1004903",
      "과목명": "채플",
      "학부(과)": "사회복지학과",
      "학년": "1",
      "이수구분": "채플",
      "영역구분": "",
      "학점": "0",
      "교수명": "오성규",
      "수업시간/장소": "화8(사무엘관110호강의실)",
      "수업시간": "화8",
      "장소": "사무엘관110호강의실"
    },
    {
      "순번": "10",
      "강좌번호": "512",
      "과목코드": "1001119",
      "과목명": "생활과 윤리",
      "학부(과)": "사회복지학과",
      "학년": "2",
      "이수구분": "교양필수",
      "영역구분": "",
      "학점": "2",
      "교수명": "오성규",
      "수업시간/장소": "수2~3(사무엘관109호강의실)",
      "수업시간": "수2~3",
      "장소": "사무엘관109호강의실"
    },
    {
      "순번": "11",
      "강좌번호": "511",
      "과목코드": "1002137",
      "과목명": "사회복지실천론",
      "학부(과)": "사회복지학과",
      "학년": "2",
      "이수구분": "전공필수",
      "영역구분": "",
      "학점": "3",
      "교수명": "김은재",
      "수업시간/장소": "목2~4(사무엘관107호강의실)",
      "수업시간": "목2~4",
      "장소": "사무엘관107호강의실"
    },
    {
      "순번": "12",
      "강좌번호": "510",
      "과목코드": "1004048",
      "과목명": "인간행동과 사회환경",
      "학부(과)": "사회복지학과",
      "학년": "2",
      "이수구분": "전공필수",
      "영역구분": "",
      "학점": "3",
      "교수명": "조미숙",
      "수업시간/장소": "화2~4(사무엘관107호강의실)",
      "수업시간": "화2~4",
      "장소": "사무엘관107호강의실"
    },
    {
      "순번": "13",
      "강좌번호": "509",
      "과목코드": "1000422",
      "과목명": "가족복지론",
      "학부(과)": "사회복지학과",
      "학년": "2",
      "이수구분": "전공선택",
      "영역구분": "",
      "학점": "3",
      "교수명": "윤주연",
      "수업시간/장소": "화6~8(사무엘관107호강의실)",
      "수업시간": "화6~8",
      "장소": "사무엘관107호강의실"
    },
    {
      "순번": "14",
      "강좌번호": "508",
      "과목코드": "1004498",
      "과목명": "정신건강사회복지론",
      "학부(과)": "사회복지학과",
      "학년": "2",
      "이수구분": "전공선택",
      "영역구분": "",
      "학점": "3",
      "교수명": "민병록",
      "수업시간/장소": "월4~6(사무엘관109호강의실)",
      "수업시간": "월4~6",
      "장소": "사무엘관109호강의실"
    },
    {
      "순번": "15",
      "강좌번호": "1576",
      "과목코드": "1004903",
      "과목명": "채플",
      "학부(과)": "사회복지학과",
      "학년": "2",
      "이수구분": "채플",
      "영역구분": "",
      "학점": "0",
      "교수명": "오성규",
      "수업시간/장소": "월3(대강당(메인))",
      "수업시간": "월3",
      "장소": "대강당(메인)"
    },
    {
      "순번": "16",
      "강좌번호": "532",
      "과목코드": "1002131",
      "과목명": "사회복지법제와 실천",
      "학부(과)": "사회복지학과",
      "학년": "3",
      "이수구분": "전공필수",
      "영역구분": "",
      "학점": "3",
      "교수명": "노기남",
      "수업시간/장소": "금2~4(사무엘관107호강의실)",
      "수업시간": "금2~4",
      "장소": "사무엘관107호강의실"
    },
    {
      "순번": "17",
      "강좌번호": "531",
      "과목코드": "1002153",
      "과목명": "사회복지현장실습",
      "학부(과)": "사회복지학과",
      "학년": "3",
      "이수구분": "전공필수",
      "영역구분": "",
      "학점": "3",
      "교수명": "조미숙",
      "수업시간/장소": "월2~4(사무엘관108호(PBL소형)강의실)",
      "수업시간": "월2~4",
      "장소": "사무엘관108호(PBL소형)강의실"
    },
    {
      "순번": "18",
      "강좌번호": "529",
      "과목코드": "1004820",
      "과목명": "지역사회복지론",
      "학부(과)": "사회복지학과",
      "학년": "3",
      "이수구분": "전공필수",
      "영역구분": "",
      "학점": "3",
      "교수명": "정종화",
      "수업시간/장소": "수3~5(사무엘관107호강의실)",
      "수업시간": "수3~5",
      "장소": "사무엘관107호강의실"
    },
    {
      "순번": "19",
      "강좌번호": "528",
      "과목코드": "1001346",
      "과목명": "사회복지와 문화다양성",
      "학부(과)": "사회복지학과",
      "학년": "3",
      "이수구분": "전공선택",
      "영역구분": "",
      "학점": "3",
      "교수명": "김은재",
      "수업시간/장소": "목6~8(사무엘관107호강의실)",
      "수업시간": "목6~8",
      "장소": "사무엘관107호강의실"
    },
    {
      "순번": "20",
      "강좌번호": "527",
      "과목코드": "1002966",
      "과목명": "아동복지론",
      "학부(과)": "사회복지학과",
      "학년": "3",
      "이수구분": "전공선택",
      "영역구분": "",
      "학점": "3",
      "교수명": "조미숙",
      "수업시간/장소": "화6~8(사무엘관108호(PBL소형)강의실)",
      "수업시간": "화6~8",
      "장소": "사무엘관108호(PBL소형)강의실"
    },
    {
      "순번": "21",
      "강좌번호": "526",
      "과목코드": "1005320",
      "과목명": "프로그램개발과 평가",
      "학부(과)": "사회복지학과",
      "학년": "3",
      "이수구분": "전공선택",
      "영역구분": "",
      "학점": "3",
      "교수명": "윤재영",
      "수업시간/장소": "수6~8(사무엘관108호(PBL소형)강의실)",
      "수업시간": "수6~8",
      "장소": "사무엘관108호(PBL소형)강의실"
    },
    {
      "순번": "22",
      "강좌번호": "1577",
      "과목코드": "1004903",
      "과목명": "채플",
      "학부(과)": "사회복지학과",
      "학년": "3",
      "이수구분": "채플",
      "영역구분": "",
      "학점": "0",
      "교수명": "오성규",
      "수업시간/장소": "수2(대강당(메인))",
      "수업시간": "수2",
      "장소": "대강당(메인)"
    },
    {
      "순번": "23",
      "강좌번호": "516",
      "과목코드": "1002120",
      "과목명": "사회보장론",
      "학부(과)": "사회복지학과",
      "학년": "4",
      "이수구분": "전공선택",
      "영역구분": "",
      "학점": "3",
      "교수명": "노기남",
      "수업시간/장소": "수6~8(사무엘관107호강의실)",
      "수업시간": "수6~8",
      "장소": "사무엘관107호강의실"
    },
    {
      "순번": "24",
      "강좌번호": "515",
      "과목코드": "1002142",
      "과목명": "사회복지자료 분석론",
      "학부(과)": "사회복지학과",
      "학년": "4",
      "이수구분": "전공선택",
      "영역구분": "",
      "학점": "3",
      "교수명": "최미혜",
      "수업시간/장소": "목2~4(제1실습관310호(전산원관리)컴퓨터강의실)",
      "수업시간": "목2~4",
      "장소": "제1실습관310호(전산원관리)컴퓨터강의실"
    },
    {
      "순번": "25",
      "강좌번호": "514",
      "과목코드": "1002156",
      "과목명": "사회복지현장심화실습",
      "학부(과)": "사회복지학과",
      "학년": "4",
      "이수구분": "전공선택",
      "영역구분": "",
      "학점": "3",
      "교수명": "조미숙",
      "수업시간/장소": "월2~4(미지정)",
      "수업시간": "월2~4",
      "장소": "미지정"
    },
    {
      "순번": "26",
      "강좌번호": "1621",
      "과목코드": "1006564",
      "과목명": "채플(온라인)",
      "학부(과)": "사회복지학과",
      "학년": "4",
      "이수구분": "채플",
      "영역구분": "",
      "학점": "0",
      "교수명": "오성규",
      "수업시간/장소": "금14(온라인)",
      "수업시간": "금14",
      "장소": "온라인"
    }
  ]
}